{"ghc":"ghc","nfs-common":"nfs-utils","libtermkey1":"libtermkey","love":"love","libsensors-dev":"lm-sensors","unpaper":"unpaper","libvips-doc":"vips","libvdpau1":"libvdpau","liblog4cpp5-dev":"log4cpp","python3-aiorpcx":"aiorpcx","libfl-dev":"flex","libquazip5-dev":"quazip","librubberband-dev":"rubberband","libkf5notifyconfig-dev":"knotifyconfig","libortp-dev":"ortp","pylint":"pylint","libssl-dev":"openssl","python3-numpy":"numpy","liblua5.4-dev":"lua","sdcc":"sdcc","libimlib2-dev":"imlib2","abootimg":"abootimg","libgtk-vnc-2.0-dev":"gtk-vnc","libnfsidmap-dev":"nfs-utils","libxcb-dpms0-dev":"libxcb","libgtksourceview-3.0-1":"gtksourceview","buildbot-worker":"buildbot-worker","harvid":"harvid","libkf5archive-dev":"karchive","attr":"attr","libwxgtk-webview3.0-gtk3-dev":"wxwidgets","qml-module-org-kde-quickcharts":"kquickcharts","tcl8.6":"tcl","ocaml-findlib":"ocaml-findlib","libcereal-dev":"cereal","gtk2-engines-pixbuf":"gtk+","python3-unidecode":"unidecode","libmspack-dev":"libmspack","desktop-file-utils":"desktop-file-utils","python3-mutagen":"mutagen","byacc":"byacc","libaudit-dev":"audit","libsmpeg-dev":"smpeg","liblua5.3-0":"lua","brltty":"brltty","libvirt-daemon-system":"libvirt","python3-dev":"python3","pipewire-pulse":"pipewire","libhyphen-dev":"hyphen","libgstreamer1.0-0":"gstreamer","libnotify-dev":"libnotify","libgnutls-dev":"gnutls","liblinphone10":"liblinphone","gir1.2-freedesktop":"gobject-introspection","python3-traitlets":"traitlets","libfishsound1-dev":"libfishsound","tk-dev":"tk","libthai-dev":"libthai","python3-simplejson":"simplejson","libmp3lame-dev":"lame","scdoc":"scdoc","libseat-dev":"seatd","libprotobuf-dev":"protobuf","liballegro4.2-dev":"allegro","libturbojpeg0-dev":"libjpeg-turbo","gnupg1":"gnupg","libkf5config-bin":"kconfig","libwavpack-dev":"wavpack","fp-units-math":"fpc","libwin-hivex-perl":"hivex","libkf5globalaccel-dev":"kglobalaccel","libgtkglext1-doc":"gtkglext","xorriso":"xorriso","librocksdb-dev":"rocksdb","hdf5-tools":"hdf5","libpdal-dev":"pdal","libxmp-dev":"libxmp","libbrotli-dev":"brotli","libgnome-desktop-3-dev":"gnome-desktop","libxcb-cursor-dev":"xcb-util-cursor","libpari-dev":"pari","gsl-bin":"gsl","libcddb2-dev":"libcddb","libkf5networkmanagerqt-dev":"networkmanager-qt","liblapack-dev":"lapack","libkf5kcmutils-dev":"kcmutils","mono-mcs":"mono","libxcb-composite0-dev":"libxcb","hledger":"hledger","gstreamer1.0-pulseaudio":"gstreamer","libnotify4":"libnotify","libdbusmenu-gtk3-dev":"libdbusmenu-gtk3","libsqlite3-dev":"sqlite","faba-icon-theme":"faba-icon-theme","python3-flask":"flask","fcitx5-modules":"fcitx5","libck-dev":"ck","libc-ares-dev":"c-ares","libyaml-dev":"libyaml","help2man":"help2man","postgresql":"postgresql","python3-matplotlib":"matplotlib","libneon27-dev":"neon","libedataserverui1.2-dev":"evolution-data-server","gstreamer1.0-plugins-good":"gstreamer","libmp3lame0":"lame","libkf5akonadimime-dev":"akonadi-mime","libpyml-ocaml-dev":"pyml","libfm-gtk-dev":"libfm","libnewt-dev":"newt","libalkimia5-dev":"alkimia","libgdal1-dev":"gdal","potrace":"potrace","acme":"acme","gir1.2-udisks-2.0":"udisks","libguestfs-dev":"libguestfs","libmpcdec-dev":"libmpcdec","liblc3-dev":"liblc3","libx264-dev":"x264","libblockdev-btrfs-dev":"libblockdev","gi-docgen":"gi-docgen","libzita-resampler-dev":"zita-resampler","fontconfig":"fontconfig","libavahi-core-dev":"avahi","libshp-dev":"shapelib","libebml-dev":"libebml","libdumb1-dev":"dumb","libarchive-tools":"libarchive","libshhmsg1-dev":"shhmsg","libceres-dev":"ceres-solver","libalut-dev":"freealut","libmagic-dev":"file","x11proto-xext-dev":"xorgproto","libgirepository1.0-doc":"gobject-introspection","magic-wormhole":"magic-wormhole","libsoup-3.0-dev":"libsoup","python3-keyrings.alt":"keyrings.alt","libusbmuxd-tools":"libusbmuxd","libfltk1.3-dev":"fltk","libogg0":"libogg","libkrb5-dev":"libkrb5","xmlbeans":"xmlbeans","libwayland-egl-backend-dev":"wayland","python-setuptools-doc":"setuptools","libnss3":"nss","libbdd-dev":"buddy","python3-pylsp":"python-lsp-server","python3-pynput":"pynput","libharfbuzz-dev":"harfbuzz","libetpan-dev":"libetpan","emacs24-nox":"emacs","libwv-dev":"wv","libmotif-dev":"motif","python3-jinja2-time":"jinja2-time","libplplot-dev":"plplot","libxfixes-dev":"libXfixes","libselinux1-dev":"libselinux","libvirglrenderer-dev":"virglrenderer","libxshmfence-dev":"libxshmfence","python3-pyasn1":"pyasn1","gir1.2-gspell-1":"gspell","libgmp-dev":"gmp","libportal-dev":"libportal","itstool":"itstool","antlr3":"antlr","libiso9660++-dev":"libcdio","libcurl3-gnutls":"curl","libaudio-dev":"nas","libgts-bin":"gts","python3-cherrypy3":"cherrypy","e2fsprogs":"e2fsprogs","maliit-framework-dev":"maliit-framework","python3-pyside2.qtwebchannel":"pyside2","libev-libevent-dev":"libev","libgig-dev":"libgig","libsigsegv-dev":"libsigsegv","phoc":"phoc","libfox-1.6-dev":"fox","guestfish":"libguestfs","youtube-dl":"youtube-dl","ctags":"ctags","cargo":"cargo","libieee1284-3-dev":"libieee1284","libunbound-dev":"unbound","gpg":"gnupg","libstd-rust-1.61":"rustc","libfm-extra-dev":"libfm-extra","libgtk-3-doc":"gtk+","openjdk-11-jre-headless":"openjdk","protobuf-c-compiler":"protobuf-c","python3-pyparsing":"pyparsing","mercurial":"mercurial","libhivex-ocaml-dev":"hivex","qt5-qmake:native":"qt","bubblewrap":"bubblewrap","libstrophe-dev":"libstrophe","sndfile-programs":"libsndfile","libmad0":"libmad","cppzmq-dev":"cppzmq","dejagnu":"dejagnu","python3-sqlparse":"sqlparse","libhighlight-perl":"highlight","python3-gi":"pygobject","libpthread-stubs0-dev":"libpthread-stubs","libfreeaptx-dev":"libfreeaptx","slapd":"openldap","libxml2":"libxml2","libpcsclite-dev":"pcsclite","python3-unbound":"unbound","liborc-0.4-dev":"orc","libvte-2.91-gtk4-dev":"vte","libgumbo-dev":"gumbo","gnumeric":"gnumeric","libguestfs-tools":"libguestfs","libuv1-dev:native":"libuv","host":"bind","python3-imath":"imath","libcurl3-dev":"curl","python3":"python3","python3-alembic":"alembic","librttopo-dev":"librttopo","xfslibs-dev":"xfsprogs","libclxclient-dev":"libclxclient","fuse3":"fuse","qtmultimedia5-dev":"qtmultimedia","libdevmapper-dev":"lvm2","libstoken-dev":"stoken","libmbim-utils":"libmbim","python3-pygame-sdl2":"pygame_sdl2","qemu-system-mips":"qemu","libfuse3-dev":"fuse","gstreamer1.0-plugins-ugly":"gstreamer","libibumad-dev":"rdma-core","llvm-14-dev":"llvm","python3-openshot":"libopenshot","libpsl-dev":"libpsl","capnproto":"capnproto","libdbus-glib-1-dev":"dbus-glib","cython3":"cython","coinor-libcoinmp-dev":"CoinMP","python3-eyed3":"eyeD3","libblockdev-lvm-dev":"libblockdev","gnustep-make":"gnustep-make","kmod":"kmod","libwlroots-dev":"wlroots","liblz-dev":"lzlib","libleatherman-dev":"leatherman","libcbor-dev":"libcbor","umockdev":"umockdev","libssh-dev":"libssh","libcdio-cdda-dev":"libcdio-paranoia","libssl1.1":"openssl","libgdbm-dev":"gdbm","libblockdev-btrfs2":"libblockdev","libedata-cal2.0-dev":"evolution-data-server","libegl-dev":"libglvnd","libesmtp-dev":"libESMTP","libtraceevent-dev":"libtraceevent","libkf5declarative-dev":"kdeclarative","libgrilo-0.3-dev":"grilo","gir1.2-libvirt-glib-1.0":"libvirt-glib","qml-module-org-kde-kitemmodels":"kitemmodels","libopencsg-dev":"opencsg","libbullet-dev":"bullet","libgtkd-3-dev":"gtkd","libblosc-dev":"c-blosc","apktool":"apktool","librsvg2-bin":"librsvg","python3-pyside2.qtgui":"pyside2","riemann-c-client":"riemann-c-client","python3-identify":"identify","libglu1-mesa-dev":"glu","libblockdev-part2":"libblockdev","libhdf5-serial-dev":"hdf5","libvips-tools":"vips","libminiupnpc-dev":"miniupnpc","libkf5plotting-dev":"kplotting","libmarble-dev":"marble","abook":"abook","pslib-dev":"pslib","libgranite-dev":"granite","python3-listparser":"listparser","xmlto":"xmlto","gir1.2-xfconf-0":"xfconf","python3-dbus":"dbus-python","libdocopt-dev":"docopt.cpp","libtool-bin":"libtool","libmount-dev":"util-linux","libmanette-0.2-dev":"libmanette","php-dev":"php","libserf-dev":"serf","libmwaw-dev":"libmwaw","liballegro4-dev":"allegro","libmypaint-dev":"libmypaint","libmuparser-dev":"muparser","gnome-icon-theme":"gnome-icon-theme","liblucene++-dev":"lucene++","libsword-dev":"sword","python3-zope.interface":"zope.interface","libsrtp2-dev":"libsrtp","libgtkmm-2.4-dev":"gtkmm","libwpd-dev":"libwpd","hwloc":"hwloc","liblensfun-dev":"lensfun","qemu-system-arm":"qemu","libxcb1-dev":"libxcb","libreadline-gplv2-dev":"readline","puredata-dev":"puredata","libcrossguid-dev":"crossguid","libbabl-dev":"babl","libchamplain-gtk-0.12-dev":"libchamplain","libxcb-randr0-dev":"libxcb","libsratom-dev":"sratom","python3-ipykernel":"ipykernel","libtss2-dev":"tpm2-tss","libxres-dev":"libXres","fuse":"fuse","libgmime-3.0-dev":"gmime","libbelr-dev":"belr","libxrender-dev":"libXrender","libkf5purpose-dev":"purpose","flex":"flex","libxslt1-dev":"libxslt","libcairo-gobject2":"cairo","libxcursor-dev":"libXcursor","portaudio19-dev":"portaudio","lynx":"lynx","autogen":"autogen","cvs":"cvs","libhwloc-dev":"hwloc","libyaml-cpp-dev":"libyaml-cpp","libxpresent-dev":"libXpresent","libkf5activitiesstats-dev":"kactivities-stats","libbox2d-dev":"box2d","python3-pygame":"pygame","spirv-headers":"spirv-headers","libdouble-conversion-dev":"double-conversion","libosmesa6-dev":"mesa","emacs-nox":"emacs","libupower-glib-dev":"upower","libkf5widgetsaddons-dev":"kwidgetsaddons","tcllib-critcl":"tcl","qemu-system-sparc":"qemu","maliit-framework":"maliit-framework","ncurses-base":"ncurses","libv4l-dev":"v4l-utils","libkf5kjs-dev":"kjs","diffstat":"diffstat","libldns-dev":"ldns","nautilus":"nautilus","libbliss-dev":"bliss","python3-serial":"pyserial","tor":"tor","libcap2-dev":"libcap","libexttextcat-dev":"libexttextcat","libgweather-4-dev":"libgweather","kdepim-runtime":"kdepim-runtime","fluidsynth":"fluidsynth","libdrm-dev":"libdrm","libmarisa-dev":"marisa","python3-pyside2.qtsvg":"pyside2","jupyter-nbformat":"nbformat","libx11-6":"libX11","python3-slixmpp":"slixmpp","qemu-user":"qemu","libxy-dev":"xylib","crystal-doc":"crystal","libanjuta-dev":"anjuta","libvamp-hostsdk3v5":"vamp-plugin-sdk","python3-pytest-localserver":"pytest-localserver","libestr-dev":"libestr","python3-libtorrent":"libtorrent-rasterbar","libcddb-dev":"libcddb","libxaw7-dev":"libXaw","libpython3-dev":"python","libglib2.0-doc":"glib","asciidoc":"asciidoc","libefivar-dev":"efivar","libtsm-dev":"libtsm","libqalculate-dev":"libqalculate","libnozzle-dev":"kronosnet","libghc-hslogger-dev":"hslogger","lame":"lame","liblouis-dev":"liblouis","libwayland-server0":"wayland","fping":"fping","libcue-dev":"libcue","libwxgtk3.0-gtk3-dev":"wxwidgets","libcjson-dev":"cjson","libspice-client-gtk-3.0-dev":"spice-gtk","libiio-dev":"libiio","libticcutils-dev":"ticcutils","libanthyinput-dev":"anthy","libriemann-client-dev":"riemann-c-client","fortune-mod":"fortune-mod","libvirt-daemon":"libvirt","python3-pwquality":"libpwquality","evolution":"evolution","cramfsswap":"cramfsswap","libchewing3-dev":"libchewing","gpsd":"gpsd","libmenhir-ocaml-dev":"menhir","libptytty-dev":"libptytty","libx11-xcb-dev":"libX11","libspeechd-dev":"speech-dispatcher","libglyr-dev":"glyr","llvm-13-dev":"llvm","soapysdr-module-all":"soapysdr","ruby3.1:native":"ruby","kalendarac":"akonadi-calendar","enjarify":"enjarify","libatspi2.0-dev":"at-spi2-core","fpc-source":"fpc","cups-daemon":"cups","libquotient-dev":"libquotient","libsecret-1-dev":"libsecret","qml-module-org-kde-kwindowsystem":"kdeclarative","libbtbb-dev":"libbtbb","libwayland-bin":"wayland","poppler-data":"poppler-data","libecal2.0-dev":"evolution-data-server","procps":"procps","dmsetup-udeb":"lvm2","osinfo-db-tools":"osinfo-db-tools","python3-cairo-dev":"pycairo","libjq-dev":"jq","weasyprint":"weasyprint","python3-deepdiff":"deepdiff","appstream-util":"appstream-glib","kinit":"kinit","ant":"ant","qml-module-org-kde-kquickimageeditor":"kquickimageeditor","libmunge-dev":"munge","ksystemstats":"ksystemstats","borgbackup":"borgbackup","x11proto-xinerama-dev":"xorgproto","libhamlib++-dev":"hamlib","libdhash-dev":"ding-libs","libfltk1.1":"fltk","ledger":"ledger","khard":"khard","ocl-icd-libopencl1":"ocl-icd","python3-scapy":"scapy","freerdp2-x11":"freerdp","libsox-fmt-all":"sox","python3-wxgtk4.0":"wxPython","ruby":"ruby","liblzo2-dev":"lzo","libglibmm-2.4-dev":"glibmm","python3-pynest2d":"pynest2d","python3-dkim":"dkimpy","liblxi-dev":"liblxi","libportal-gtk3-dev":"libportal-gtk3","libclucene-dev":"clucene-core","libvncserver-dev":"libvncserver","xbitmaps":"xbitmaps","libzmf-dev":"libzmf","libgnome-menu-3-dev":"gnome-menus","libslirp-dev":"libslirp","libjxr-dev":"jxrlib","python3-netifaces":"netifaces","libegl1-mesa-dev":"mesa","xsltproc":"libxslt","qtwebengine5-dev":"qtwebengine","libidn2-dev":"libidn","python3-pyls-spyder":"pyls-spyder","python3-selinux":"libselinux","cmark":"cmark","rdma-core":"rdma-core","guile-2.2":"guile","libgraphicsmagick++1-dev":"graphicsmagick","kross-dev":"kross","liblrdf-dev":"lrdf","libpwquality-dev":"libpwquality","libdc1394-dev":"libdc1394","libwxgtk-webview3.2-dev":"wxwidgets","gnupg-utils":"gnupg","python3-openpyxl":"openpyxl","iverilog":"iverilog","libjson-glib-dev":"json-glib","trace-cmd":"trace-cmd","akonadi-server":"akonadi","at-spi2-core":"at-spi2-core","python3-enchant":"pyenchant","python3-btchip":"btchip-python","freetds-dev":"freetds","libhyperscan-dev":"hyperscan","libwayland-egl1":"wayland","libnetfilter-acct-dev":"libnetfilter_acct","libzmq5":"zeromq","libglu-dev":"glu","xkb-data":"xkeyboard-config","libaml-dev":"aml","libgl1-mesa-dri":"mesa","libsass1":"libsass","libcdio-dev":"libcdio","libkf5mailtransport-dev":"kmailtransport","libnftables-dev":"nftables","rustc":"rustc","libayatana-indicator-dev":"libayatana-indicator","libliftoff-dev":"libliftoff","libproj-dev":"proj","fcitx5-module-lua":"fcitx5-lua","python3-sipbuild":"sip","libgettextpo-dev":"gettext","libxcb-xkb-dev":"libxcb","libpurple-dev":"pidgin","guile-3.0":"guile","libxklavier-dev":"libxklavier","iw":"iw","libxxf86dga-dev":"libXxf86dga","ofono-dev":"ofono","libnet1-dev":"libnet","less":"less","numix-icon-theme":"numix-icon-theme","python3-voluptuous":"voluptuous","libgle-dev":"gle","apksigner":"apksigner","libgdk-pixbuf-2.0-dev":"gdk-pixbuf","libstilview-dev":"libsidplayfp","libkpipewire-dev":"kpipewire","python3-pyqt5.qtwebchannel":"PyQt5","qtkeychain-qt5-dev":"qtkeychain","libphonon4qt5-dev":"phonon","python3-pyscard":"pyscard","libcap2-bin":"libcap","tcl8.6-dev":"tcl","python3-pyfuse3":"pyfuse3","libxt-dev":"libXt","halibut":"halibut","libsoup2.4-doc":"libsoup","freecell-solver-bin":"freecell-solver","xvfb":"xorg-server","libcap-dev":"libcap","libjemalloc-dev":"jemalloc","libtelepathy-logger-dev":"telepathy-logger","libmemcached-dev":"libmemcached","libexempi-dev":"exempi","gir1.2-gtk-4.0":"gtk4","libx86emu-dev":"libx86emu","libosmgpsmap-1.0-dev":"osm-gps-map","libatk-adaptor":"at-spi2-core","libgtkspell-dev":"gtkspell","python3-manuel":"manuel","libgcrypt20-dev":"libgcrypt","docbook-xml":"docbook-xml","libkf5identitymanagement-dev":"kidentitymanagement","libhdf5-dev":"hdf5","libibmad-dev":"libibmad","libxcb-image0-dev":"xcb-util-image","libssh2-1-dev":"libssh2","qml-module-org-kde-kquickcontrols":"kdeclarative","libxsimd-dev":"xsimd","python3-fake-factory":"faker","libexpat1-dev":"expat","libhunspell-dev":"hunspell","qml-module-org-kde-charts":"kqtquickcharts","comerr-dev":"e2fsprogs","libcheese-gtk-dev":"cheese","liboauth-dev":"liboauth","python3-cookiecutter":"cookiecutter","cmake3":"cmake","gstreamer1.0-alsa":"gstreamer","libmono-i18n4.0-cil":"mono","systemd-container":"systemd","libfm-qt-dev":"libfm-qt","xdotool":"xdotool","cppcheck":"cppcheck","python3-pylint-celery":"pylint-celery","ocaml-nox":"ocaml","neko":"neko","libcgal-dev":"cgal","libtwolame-dev":"twolame","python3-consul":"python-consul","libgoffice-0.10-dev":"goffice","yasm":"yasm","okular-dev":"okular","libiso9660-dev":"libcdio","libenchant-2-dev":"enchant","libevent-dev":"libevent","python3-setuptools-scm-git-archive":"setuptools-scm-git-archive","libkf5unitconversion-dev":"kunitconversion","speech-dispatcher":"speech-dispatcher","libsuma-dev":"sumalibs","libflann-dev":"flann","libcups2-dev":"cups","libspnav-dev":"libspnav","libudisks2-dev":"udisks","libimecore-dev":"libime","libsmbios-dev":"libsmbios","libflac-dev":"flac","libconfig-dev":"libconfig","jupyter-core":"jupyter_core","ofono":"ofono","libmbt-dev":"mbt","libglade2-dev":"libglade","libsepol2":"libsepol","enscript":"enscript","libcxxtools-dev":"cxxtools","libostree-dev":"ostree","acl-dev":"acl","emacs25-nox":"emacs","gobject-introspection":"gobject-introspection","texi2html":"texi2html","python3-flask-babel":"Flask-Babel","libglew-dev":"glew","libibus-1.0-dev":"ibus","python3-linux-procfs":"python-linux-procfs","dvdauthor":"dvdauthor","pps-tools":"pps-tools","python3-avahi":"avahi","libfilezilla-dev":"libfilezilla","gpm":"gpm","python3-pexpect":"pexpect","libgupnp-dlna-2.0-dev":"gupnp-dlna","libi2c-dev":"i2c-tools","python3-pyroma":"pyroma","libshout3-dev":"libshout","libnss3-tools":"nss","libkf5guiaddons-dev":"kguiaddons","python3-pycountry":"pycountry","liburcu-dev":"liburcu","frogdata":"frogdata","libotr5-dev":"libotr","libg15-dev":"libg15","libghc-cpphs-dev":"cpphs","libleveldb-dev":"leveldb","python3-gtts":"gtts","libkf5akonadisearch-plugins":"akonadi-search","parallel":"parallel","gstreamer1.0-plugins-bad":"gstreamer","libmhash-dev":"mhash","libpresage-dev":"presage","libkf5auth-dev":"kauth","libsvm-dev":"libsvm","libcamlimages-ocaml-dev":"camlimages","libircclient-dev":"libircclient","llvm-":"llvm","python3-pychromecast":"pychromecast","python3-wcwidth":"wcwidth","libev-dev":"libev","libsdl-image1.2-dev":"SDL_image","libusb2-dev":"libusb","libgdiplus":"libgdiplus","isolinux":"syslinux","rust-clippy":"rustc","libcapnp-dev":"capnproto","libass-dev":"libass","libfcitx5-qt-dev":"fcitx5-qt","python3-chardet":"chardet","binutils-multiarch":"binutils","gjs":"gjs","wordnet-dev":"wordnet","libtoxcore-dev":"libtoxcore","libraptor2-dev":"raptor2","tk8.6-dev":"tk","cifs-utils":"cifs-utils","python3-annexremote":"annexremote","libnftnl-dev":"libnftnl","python3-qstylizer":"qstylizer","libebook1.2-dev":"evolution-data-server","nasm":"nasm","libvips-dev":"vips","libqmobipocket-dev":"kdegraphics-mobipocket","stubby":"getdns","libncurses-dev":"ncurses","go-md2man":"go-md2man","gyp":"gyp","luit":"luit","libglvnd-core-dev":"libglvnd","libgtkdatabox-dev":"gtkdatabox","python3-funcparserlib":"funcparserlib","ocl-icd-opencl-dev":"ocl-icd","libkf5tnef-dev":"ktnef","libqt5x11extras5-dev":"qt","libpostproc-dev":"ffmpeg","nxproxy":"nx-libs","libmono-compilerservices-symbolwriter4.0-cil":"mono","python3-notmuch":"notmuch","libopensmtpd-dev":"libopensmtpd","libfwupd-dev":"fwupd","python3-kitchen":"kitchen","libantlr3c-dev":"libantlr3c","libjsoncpp-dev":"jsoncpp","libkf5bookmarks-dev":"kbookmarks","libxcb-xtest0-dev":"libxcb","libqxmpp-dev":"qxmpp","python3-pandas":"pandas","libfcgi-dev":"fcgi","libpyside2-dev":"pyside2","libgts-dev":"gts","libuv1-dev":"libuv","kaddressbook":"kaddressbook","libkf5pty-dev":"kpty","libmatio-dev":"matio","libwrap0-dev":"tcp-wrappers","libxau-dev":"libXau","qml-module-org-kde-kcoreaddons":"kdeclarative","libunshield-dev":"unshield","fcitx-libs-dev":"fcitx","libmtp-dev":"libmtp","rrdcached":"rrdtool","python3-m2crypto":"M2Crypto","libantlr-dev":"antlr","python3-sphinx":"sphinx","python3-pytestqt":"pytest-qt","libvarnishapi-dev":"varnish","libbabeltrace-ctf-dev":"babeltrace","bsdextrautils":"util-linux","libreadline6-dev":"readline","libwps-dev":"libwps","tcllib":"tcllib","libstorm-dev":"StormLib","ppp":"ppp","fluid":"fltk","expect":"expect","libsodium-dev":"libsodium","libjcat-dev":"libjcat","rep":"librep","bup":"bup","python3-tlsh":"tlsh","maxima-doc":"maxima","libmrss0-dev":"libmrss","tk8.6":"tk","libperl4-corelibs-perl":"perl","openjdk-11-jdk-headless":"openjdk","libtre-dev":"tre","json-glib-tools":"json-glib","gegl":"gegl","libosmium2-dev":"libosmium","unzip":"unzip","rep-gtk":"rep-gtk","libcanberra-pulse":"libcanberra","timidity":"timidity","libaubio5":"aubio","libdrumstick-dev":"drumstick","xwayland":"xwayland","vde2":"vde2","libgit2-glib-1.0-dev":"libgit2-glib","jupyter-client":"jupyter_client","libxi-dev":"libXi","qemu-system-x86":"qemu","extra-cmake-modules":"extra-cmake-modules","liblua5.1-dev":"lua","breeze-icon-theme":"breeze-icons","fp-units-gtk2":"fpc","libblkid-dev":"util-linux","libgeos-dev":"geos","libplacebo-dev":"libplacebo","libvte-2.91-dev":"vte","pydocstyle":"pydocstyle","libtcl8.6":"tcl","libkf5akonadisearch-bin":"akonadi-search","freeglut3-dev":"freeglut","libspatialite-dev":"libspatialite","libblockdev-loop2":"libblockdev","qml-module-qtquick-templates2":"qtquickcontrols","ruby3.1-doc":"ruby","libgwengui-gtk3-dev":"gwenhywfar","camlp5":"camlp5","libstroke0-dev":"libstroke","libcli-dev":"libcli","po4a":"po4a","python3-rope":"rope","gpg-wks-client":"gnupg","libghc-hscolour-dev":"hscolour","qml-module-org-kde-ksysguard":"libksysguard","libmpfi-dev":"mpfi","libllvm14":"llvm","kded5-dev":"kded","libimetable-dev":"libime","kwin-common":"kwin","libblockdev-part-dev":"libblockdev","man-db":"man-db","libkf5itemviews-dev":"kitemviews","sox":"sox","ragel":"ragel","libavc1394-dev":"libavc1394","libscalapack-mpi-dev":"scalapack","libudev-dev":"systemd","libsdl-net1.2-dev":"SDL_net","libebook-contacts1.2-dev":"evolution-data-server","guile-library":"guile","openbox":"openbox","libphonon4qt5experimental-dev":"phonon","python3-munkres":"munkres","tcpdump":"tcpdump","sound-theme-freedesktop":"sound-theme-freedesktop","libefiboot-dev":"efivar","libmdds-dev":"mdds","mopidy":"mopidy","inkscape":"inkscape","frei0r-plugins-dev":"frei0r-plugins","python3-praw":"praw","libvulkan-dev":"vulkan-loader","libtinfo-dev":"ncurses","python3-xhtml2pdf":"xhtml2pdf","libxcb-xfixes0-dev":"libxcb","libgeotiff-dev":"libgeotiff","libffmpeg-nvenc-dev":"nv-codec-headers","libphodav-3.0-dev":"phodav","libgraphics-magick-perl":"graphicsmagick","syslinux-common":"syslinux","libnotmuch-dev":"notmuch","libppl-dev":"ppl","python3-jeepney":"jeepney","libdbus-1-dev":"dbus","libwoff-dev":"woff2","libfabric-dev":"libfabric","libmaxminddb-dev":"libmaxminddb","python3-pyside2.qtuitools":"pyside2","libavahi-glib-dev":"avahi","libopenmpi-dev":"openmpi","nodejs":"nodejs","python3-pyqt5.qtwebkit":"PyQt5","python-requests-doc":"requests","cabextract":"cabextract","pyqt5-dev-tools":"PyQt5","libdmapsharing-3.0-dev":"libdmapsharing","ruby-google-protobuf":"protobuf","libfido2-1":"libfido2","mypaint-brushes":"mypaint-brushes","libasound2-dev":"alsa-lib","libdbi0-dev":"libdbi","fp-units-base":"fpc","python3-pyqt5.qtsvg":"PyQt5","libglc-dev":"quesoglc","python3-nbformat":"nbformat","dbus-bin":"dbus","genisoimage":"cdrkit","liblrdf0-dev":"lrdf","gnuplot5-qt":"gnuplot","libtss2-rc0":"tpm2-tss","python3-pycurl":"pycurl","libdvbpsi-dev":"libdvbpsi","libcrypt-dev":"libxcrypt","libxmlrpc-core-c3-dev":"xmlrpc-c","liblzo2-dev:native":"lzo","python3-etcd":"python-etcd","systemd-coredump":"systemd","x11proto-xf86dri-dev":"xorgproto","python3-isodate":"isodate","libgnome-desktop-4-dev":"gnome-desktop","libgssdp-1.2-dev":"gssdp","libgl1-mesa-glx":"libGL","python3-pymediainfo":"pymediainfo","libpipewire-0.3-dev":"pipewire","libmpg123-dev":"mpg123","mp3gain":"mp3gain","libreadline5-dev":"readline","gsettings-desktop-schemas":"gsettings-desktop-schemas","python3-jenkins":"python-jenkins","libxdo-dev":"xdotool","frei0r-plugins":"frei0r-plugins","libdvdcss2":"libdvdcss","gir1.2-nm-1.0":"networkmanager","icmake":"icmake","libxml++2.6-dev":"libxml++","lua-filesystem":"luafilesystem","mutter-common":"mutter","libclang-14-dev":"clang","autoconf2.13":"autoconf","trousers":"trousers","libcmark-dev":"cmark","udisks2":"udisks","libjpeg-turbo-progs":"libjpeg-turbo","libvdpau-dev":"libvdpau","ostree":"ostree","mm-common":"mm-common","libdiscid-dev":"libdiscid","yelp-xsl":"yelp-xsl","mono-runtime":"mono","xa65":"xa","python3-plist":"libplist","gir1.2-gsound-1.0":"gsound","sharutils":"sharutils","fp-units-rtl":"fpc","libneon27-gnutls-dev":"neon","pulseaudio-module-gsettings":"pulseaudio","ocaml":"ocaml","synfig-examples":"synfig","libcurl-dev":"curl","libspeex-dev":"speex","libblockdev-mdraid-dev":"libblockdev","python3-pyodbc":"pyodbc","guile-bytestructures":"scheme-bytestructures","liblscp-dev":"liblscp","libgtest-dev":"gtest","liburing-dev":"liburing","libmms-dev":"libmms","libcppunit-dev":"cppunit","libpcap0.8":"libpcap","curl":"curl","kscreenlocker-dev":"kscreenlocker","libchromaprint-tools":"chromaprint","libgdk-pixbuf-xlib-2.0-dev":"gdk-pixbuf-xlib","libsigrokcxx-dev":"libsigrok","libphysfs1":"physfs","fig2dev":"fig2dev","liblayershellqtinterface-dev":"layer-shell-qt","libafflib-dev":"afflib","python3-pep8-naming":"pep8-naming","rust-doc":"rustc","python3-authres":"authres","openbox-dev":"openbox","libdaemon-dev":"libdaemon","libglib2.0-dev-bin":"glib","lua5.1":"lua","liba52-0.7.4-dev":"a52dec","python3-marisa":"marisa","libnl-genl-3-dev":"libnl","libdevil-dev":"libdevil","libgflags-dev":"gflags","peg":"peg","libmodbus-dev":"libmodbus","fuse2fs":"fuse","libsdl2-gfx-dev":"SDL","libkf5idletime-dev":"kidletime","libffcall-dev":"libffcall","libgtk2.0-dev":"gtk+","emacs-gtk":"emacs","python3-prettytable":"prettytable","libyascreen-dev":"yascreen","libftgl-dev":"ftgl","libkf5solid-dev":"solid","wayland-protocols":"wayland-protocols","gdal-bin":"gdal","libid3tag0-dev":"libid3tag","libncursesw6":"ncurses","libcamomile-ocaml-dev":"camomile","meson":"meson","mupdf-tools":"mupdf","python3-pyroute2":"pyroute2","libssh-gcrypt-dev":"libssh","libglvnd-dev":"libglvnd","libocamlgraph-ocaml-dev":"ocamlgraph","liblouis-bin":"liblouis","clang-14":"clang","python3-pyside2.qtxml":"pyside2","libnss-wrapper":"nss_wrapper","libprocps-dev":"procps","libkeyutils-dev":"keyutils","libattr1-dev":"attr","python3-pkg-resources":"setuptools","librep16":"librep","source-highlight":"source-highlight","ssh":"openssh","libdjvulibre21":"djvulibre","libvlc-dev":"libvlc","adwaita-icon-theme":"adwaita-icon-theme","zstd":"zstd","libhdf4-alt-dev":"hdf","polkit-1-auth-agent":"polkit","python3-h5py":"h5py","fontforge-nox":"fontforge","openjdk-8-jdk-headless":"openjdk","python3-cloudpickle":"cloudpickle","libtorrent-rasterbar-dev":"libtorrent-rasterbar","gir1.2-libosinfo-1.0":"libosinfo","libcec-dev":"libcec","libkf5globalaccel-bin":"kglobalaccel","kde-config-screenlocker":"kscreenlocker","mlton-doc":"mlton","libnbd-dev":"libnbd","python3-jupyter-core":"jupyter_core","libmlt-dev":"mlt","jupyter-nbconvert":"nbconvert","socat":"socat","python3-pylint-flask":"pylint-flask","uuid-dev":"util-linux","liblz4-dev":"lz4","flatpak":"flatpak","libhandy-0.0-dev":"libhandy","qt5keychain-dev":"qtkeychain","libmpdclient-dev":"libmpdclient","libreadline5-dbg":"readline","libghc-src-exts-dev":"haskell-src-exts","libjbig2dec0-dev":"jbig2dec","libx265-dev":"x265","gpgsm":"gnupg","python3-soapysdr":"soapysdr","libglew1.5-dev":"glew","xserver-xorg-dev":"xorg-server","kquickcharts-dev":"kquickcharts","python3-ethtool":"python-ethtool","gir1.2-goocanvas-2.0":"goocanvas","libglib2.0-0":"glib","python3-musicbrainzngs":"musicbrainzngs","libportmidi-dev":"portmidi","tesseract-ocr":"tesseract","libfido2-dev":"libfido2","doxygen-latex":"doxygen","libbpf-dev":"libbpf","pandoc":"pandoc","libavahi-ui-gtk3-dev":"avahi","python3-websocket":"websocket-client","clang-15":"clang","barcode":"barcode","libglm-dev":"glm","libkf5wayland-dev":"kwayland","finger":"bsd-finger","python3-markupsafe":"markupsafe","libgdk-pixbuf2.0-dev":"gdk-pixbuf-xlib","bluez":"bluez","libtevent-dev":"tevent","liblua5.3-dev":"lua","libqt5opengl5-dev":"qt","lv2-dev":"lv2","python3-cli-helpers":"cli_helpers","libvirt-dev":"libvirt","libcacard-dev":"libcacard","v4l-utils":"v4l-utils","gir1.2-glib-2.0":"gobject-introspection","libsuil-dev":"suil","libbsd-dev":"libbsd","ktexteditor-katepart":"ktexteditor","libcurl3-gnutls-dev":"curl","libwww-perl":"libwww-perl","libstd-rust-dev":"rustc","tabix":"htslib","doxygen":"doxygen","dssi-dev":"dssi","libaspell-dev":"aspell","appstream":"appstream","libcamera-dev":"libcamera","python3-fuzzywuzzy":"fuzzywuzzy","qemu-utils":"qemu","libopencv-dev":"opencv","libgsf-1-dev":"libgsf","xplanet":"xplanet","libcdr-dev":"libcdr","dbus":"dbus","tcl-dev":"tcl","libwebrtc-audio-processing-dev":"webrtc-audio-processing","python3-ply":"ply","icoutils":"icoutils","libyang2-dev":"libyang","libmaxflow-dev":"maxflow","libgphoto2-dev":"libgphoto2","net-tools":"net-tools","libpopt-dev":"popt","python2":"python","libdrumstick-rt-backends":"drumstick","sane-utils":"sane-backends","libblockdev-crypto2":"libblockdev","python3-enrich":"enrich","python3-tqdm":"tqdm","libopts25-dev":"autogen","gnuplot-qt":"gnuplot","libdbi-dev":"libdbi","libxerces-c-dev":"xerces-c","dblatex":"dblatex","libphysfs-dev":"physfs","libevince-dev":"evince","python3-ripe-atlas-cousteau":"ripe-atlas-cousteau","glslang-dev":"glslang","libmtdev-dev":"mtdev","libmng-dev":"libmng","bind9-dnsutils":"bind","libkf5i18n-dev":"ki18n","libarpack2-dev":"arpack","python3-louis":"liblouis","gcab":"gcab","python3-spyder-kernels":"spyder-kernels","gnuplot-x11":"gnuplot","libtag-extras-dev":"taglib-extras","firebird3.0-server":"firebird","libupnp-dev":"libupnp","fp-units-gfx":"fpc","perl":"perl","libgit2-dev":"libgit2","libspa-0.2-bluetooth":"pipewire","libatk1.0-dev":"at-spi2-core","gnupg-agent":"gnupg","libxcb-xrm-dev":"xcb-util-xrm","python3-jinja2":"Jinja2","hicolor-icon-theme":"hicolor-icon-theme","libsndfile1":"libsndfile","libxcb-render-util0-dev":"xcb-util-renderutil","libmagick++-dev":"imagemagick","kirigami2-dev":"kirigami2","qemu-system-ppc":"qemu","libblockdev-swap2":"libblockdev","libyubikey-udev":"yubikey-personalization","libhttp-parser-dev":"http-parser","gir1.2-gtksource-3.0":"gtksourceview","libgtksourceviewmm-3.0-dev":"gtksourceviewmm","libotf-dev":"libotf","libsmbclient-dev":"samba","libsparsehash-dev":"sparsehash","python3-sqlite-fts4":"sqlite-fts4","gnome-shell":"gnome-shell","unclutter":"unclutter","python3-setuptools-scm":"setuptools-scm","libkaccounts-dev":"kaccounts-integration","python3-smart-open":"smart-open","libcurses-ocaml-dev":"ocaml-curses","libx11-dev":"libX11","libpfm4-dev":"libpfm","libtommath-dev":"libtommath","librime-dev":"librime","libtirpc-dev":"libtirpc","ansible-core":"ansible-core","libgif-dev":"giflib","libspatialaudio-dev":"libspatialaudio","libopenbabel-dev":"openbabel","libblockdev-crypto-dev":"libblockdev","khotkeys":"khotkeys","libffms2-dev":"ffms","rrdtool":"rrdtool","python3-ly":"python-ly","imagemagick-6.q16":"imagemagick","libkf5texteditor-dev":"ktexteditor","python3-lxml":"lxml","python3-pyflakes":"pyflakes","libspandsp-dev":"spandsp","libiksemel-dev":"iksemel","ibus-data":"ibus","guile-2.0":"guile","libxcb-damage0-dev":"libxcb","libodbc1":"unixODBC","librest-dev":"rest","libepc-dev":"libepc","libdirectfb-dev":"directfb","patool":"patool","libbz2-dev":"bzip2","python3-pil":"pillow","libkf5screen-dev":"libkscreen","libpugixml-dev":"pugixml","mono-runtime-common":"mono","libzeitgeist-2.0-dev":"zeitgeist","zlib1g-dev:native":"zlib","libndp-dev":"libndp","libgpg-error-mingw-w64-dev":"libgpg-error","libmnl-dev":"libmnl","libkf5akonadiserver-dev":"akonadi","tcl8.7-dev":"tcl","modemmanager-qt-dev":"modemmanager-qt","libhangul-dev":"libhangul","octave":"octave","fp-compiler":"fpc","libpango1.0-doc":"pango","libdeflate-dev":"libdeflate","qemu-user-binfmt":"qemu","libopencv-imgproc-dev":"opencv","libsdl2-mixer-dev":"SDL","network-manager-dev":"networkmanager","python3-potr":"python-potr","libkf5completion-dev":"kcompletion","python3-cairo-doc":"pycairo","libimobiledevice-dev":"libimobiledevice","libpng-dev":"libpng","automake":"automake","python3-slugify":"python-slugify","libepub-dev":"ebook-tools","libgupnp-1.2-dev":"gupnp","libgeocode-glib-dev":"geocode-glib","libnuma-dev":"numactl","python3-ipy":"IPy","lib32ncurses-dev":"ncurses","libcupsimage2-dev":"cups","libmaa-dev":"libmaa","libcmocka-dev":"cmocka","libsdl-ttf2.0-dev":"SDL_ttf","libruby3.1":"ruby","libkf5newstuff-dev":"knewstuff","proj-bin":"proj","emacs-lucid":"emacs","libsnmp-dev":"net-snmp","libvorbis0a":"libvorbis","libtomcrypt-dev":"libtomcrypt","libktorrent-l10n":"libktorrent","python3-dulwich":"dulwich","libbotan-2-dev":"botan","libglpk-dev":"glpk","librrds-perl":"rrdtool","python3-requests-file":"requests-file","telepathy-logger":"telepathy-logger","autoconf":"autoconf","libxmlbird-dev":"xmlbird","groff-base":"groff","libstd-rust-dev-windows":"rustc","avahi-daemon":"avahi","qml-module-org-kde-solid":"solid","libgladeui-dev":"glade","liblinphone-dev":"liblinphone","python3-pyqt5.qtopengl":"PyQt5","lxc-dev":"lxc","libprotozero-dev":"protozero","valgrind":"valgrind","python3-isort":"isort","libgtk-layer-shell0":"gtk-layer-shell","libqcsxcad0":"qcsxcad","python3-automat":"automat","libnlopt-dev":"nlopt","shared-mime-info":"shared-mime-info","zlib1g-dev":"zlib","librdkafka-dev":"rdkafka","ffmpeg":"ffmpeg","libcollection-dev":"ding-libs","gnome-session-common":"gnome-session","qml-module-org-kde-people":"kpeople","libsysfs-dev":"sysfsutils","libtss2-esys-3.0.2-0":"tpm2-tss","libshhopt1-dev":"shhopt","qml-module-org-kde-pipewire":"kpipewire","python3-pycryptodome":"pycryptodome","netpbm":"netpbm","libunwind-dev":"libunwind","libsvn-dev":"subversion","libkproperty3-dev":"kproperty","libsox-dev":"sox","python3-icu":"PyICU","python3-pygments":"pygments","dbus-daemon":"dbus","libkf5kdegames-dev":"libkdegames","libsdl-mixer1.2":"SDL_mixer","iproute":"iproute2","python3-kazoo":"kazoo","libgdamm5.0-dev":"libgdamm","librep-dev":"librep","libpackagekit-glib2-dev":"packagekit","libkf5mime-dev":"kmime","python3-typogrify":"typogrify","libgstreamer1.0-dev":"gstreamer","wcslib-dev":"wcslib","libowfat-dev":"libowfat","libfcft-dev":"fcft","konsole":"konsole","libknet-dev":"kronosnet","x11proto-dri2-dev":"xorgproto","tzdata":"tzdata","libbiblesync-dev":"biblesync","python3-xcbgen":"xcb-proto","libical-dev":"libical","libvirt-ocaml-dev":"ocaml-libvirt","qml-module-org-kde-kquickcontrolsaddons":"kdeclarative","magic-wormhole-transit-relay":"magic-wormhole-transit-relay","freeglut3":"freeglut","libtimbl-dev":"timbl","libqmi-utils":"libqmi","libkf5webkit-dev":"kdewebkit","python3-lz4":"python-lz4","python3-pylsp-black":"python-lsp-black","libglx-dev":"libglvnd","lxmenu-data":"lxmenu-data","ghc-prof":"ghc","djvulibre-bin":"djvulibre","libboost-dev":"boost","libdconf-dev":"dconf","libdb-dev":"db","docbook-xsl-ns":"docbook-xsl-ns","menhir":"menhir","libsamplerate-dev":"libsamplerate","gtk-doc-tools":"gtk-doc","libasio-dev":"asio","libgtksourceview-5-dev":"gtksourceview","wabt":"wabt","python3-pyglet":"pyglet","parted":"parted","snmp":"net-snmp","libnuma1":"numactl","libhts-dev":"htslib","libsass-dev":"libsass","qtdeclarative5-dev":"qtdeclarative","python3-pyside2.qtnetwork":"pyside2","libwebsockets-dev":"libwebsockets","libleptonica-dev":"leptonica","pipewire":"pipewire","libatk-bridge2.0-dev":"at-spi2-core","img2pdf":"img2pdf","gir1.2-gtksource-5":"gtksourceview","libtree-sitter-dev":"tree-sitter","libmsgpack-dev":"msgpack","libxkbcommon-x11-dev":"libxkbcommon","qml-module-org-kde-games-core":"libkdegames","virtualenv":"virtualenv","libkimageannotator-dev":"kimageannotator","libcapstone-dev":"capstone","mlton-runtime-alpha-linux-gnu":"mlton","liballegro-dev":"allegro","libsdl1.2-dev":"SDL","libpango1.0-dev":"pango","rust-src":"rustc","libnl-route-3-dev":"libnl","libddcutil4":"ddcutil","qml-module-org-kde-kcm":"kdeclarative","python3-ledger":"ledger","libcwiid-dev":"cwiid","gerbv":"gerbv","libime-bin":"libime","gringo":"gringo","libkf5threadweaver-dev":"threadweaver","libmad0-dev":"libmad","libusbredirhost-dev":"usbredir","kquickimageeditor-dev":"kquickimageeditor","libgoa-1.0-dev":"gnome-online-accounts","p7zip-full":"p7zip","libkf5people-dev":"kpeople","libncursesw5-dev":"ncurses","gstreamer1.0-gtk3":"gstreamer","gir1.2-pango-1.0":"pango","libspice-server-dev":"spice","emacs25":"emacs","ocaml-native-compilers":"ocaml","cups-bsd":"cups","libmodplug-dev":"libmodplug","syslinux-utils":"syslinux","traceroute":"traceroute","libzim-dev":"zimlib","selinux-utils":"libselinux","libcryptui-dev":"libcryptui","libkf5sonnet-dev":"sonnet","libxdmcp-dev":"libXdmcp","libgraphite2-dev":"graphite2","libutempter-dev":"libutempter","python3-html5lib":"html5lib","gir1.2-gupnpigd-1.0":"gupnp-igd","gnupg":"gnupg","libxft-dev":"libXft","libldap2-dev":"openldap","libgcrypt-dev":"libgcrypt","python3-gi-cairo":"pygobject","ktnef":"ktnef","libdbd-sqlite3":"libdbi-drivers","waffle-utils":"waffle","libayatana-appindicator3-dev":"libayatana-appindicator","libmd-dev":"libmd","libimage-magick-perl":"imagemagick","libnetfilter-conntrack3":"libnetfilter_conntrack","readline-common":"readline","locate":"findutils","libblockdev-loop-dev":"libblockdev","libblockdev-lvm2":"libblockdev","libfreeimage-dev":"freeimage","xmlstarlet":"xmlstarlet","libbs2b-dev":"libbs2b","bolt":"bolt","gsettings-desktop-schemas-dev":"gsettings-desktop-schemas","gstreamer1.0-libav":"gstreamer","gettext-base":"gettext","libphonenumber-dev":"phonenumber","glslang-tools":"glslang","libjansson-dev":"jansson","libxt6":"libXt","sbsigntool":"sbsigntool","python3-azure-functions-devops-build":"azure-functions-devops-build","python3-libxmp":"python-xmp-toolkit","singular":"singular","libtasn1-dev":"libtasn1","libkf5kdelibs4support-dev":"kdelibs4support","unixodbc":"unixODBC","maxima":"maxima","freerdp2-wayland":"freerdp","python3-asn1crypto":"asn1crypto","tmux":"tmux","flite1-dev":"flite","python3-txtorcon":"txtorcon","nkf":"nkf","libmetis-dev":"metis","qttools5-dev":"qttools","libkf5kio-dev":"kio","libcmdliner-ocaml-dev":"cmdliner","elfutils":"elfutils","libboogie-cil":"Boogie","mencoder":"mplayer","libiscsi-dev":"libiscsi","libnotify-bin":"libnotify","libmusicbrainz5-dev":"libmusicbrainz","libnet-dev":"libnet","libmovit-dev":"movit","libusb-dev":"libusb","libplist-dev":"libplist","libwpg-dev":"libwpg","libcifpp2":"libcifpp","fwupd-unsigned-dev":"fwupd-efi","python3-zope.component":"zope.component","fp-docs":"fpc","libipmimonitoring-dev":"freeipmi","iprange":"iprange","libiptcdata0-dev":"libiptcdata","libavdevice-dev":"ffmpeg","libwnck-3-dev":"libwnck","gir1.2-peas-1.0":"libpeas","python3-astroid":"astroid","libghc-cpphs-prof":"cpphs","fwupd":"fwupd","libquorum-dev":"corosync","python3-magic-wormhole-mailbox-server":"magic-wormhole-mailbox-server","transfig":"fig2dev","autoconf-doc":"autoconf","libtool":"libtool","librsvg2-common":"librsvg","vamp-plugin-sdk":"vamp-plugin-sdk","libgdk-pixbuf2.0-bin":"gdk-pixbuf","libgtk-layer-shell-dev":"gtk-layer-shell","libbluetooth-dev":"bluez","python3-pivy":"pivy","python3-prompt-toolkit":"prompt-toolkit","libdjvulibre-text":"djvulibre","libaio-dev":"libaio","tcl":"tcl","expat":"expat","libpst-dev":"libpst","libopenconnect-dev":"openconnect","x11proto-dev":"xorgproto","librdf0-dev":"redland","mono-utils":"mono","fcitx5-module-lua-dev":"fcitx5-lua","pim-sieve-editor":"pim-sieve-editor","libganv-dev":"ganv","ss-dev":"e2fsprogs","libsuperlu-dev":"superlu","qalc":"libqalculate","libnetfilter-conntrack-dev":"libnetfilter_conntrack","libinfinity-0.7-dev":"libinfinity","libgnt-dev":"libgnt","libdbusmenu-qt5-dev":"libdbusmenu-qt","libmatroska-dev":"libmatroska","rust-lldb":"rustc","python3-pyside2.qtwebengine":"pyside2","libkf5coreaddons-dev":"kcoreaddons","libopenal-dev":"openal-soft","libsnappy-dev":"snappy","libndpi-dev":"ndpi","libasound2":"alsa-lib","libcmap-dev":"corosync","libfontconfig1-dev":"fontconfig","libtiff5-dev":"libtiff","libraw-dev":"libraw","python3-responses":"responses","libkdecorations2-dev":"kdecoration","libfcitx5core-dev":"fcitx5","libdleyna-connector-dbus-1.0-1":"dleyna-connector-dbus","libqt5opengl5-desktop-dev":"qt","libxvidcore-dev":"xvidcore","libkf5akonadicalendar-dev":"akonadi-calendar","libparted-dev":"parted","libuv1":"libuv","libhamlib-utils":"hamlib","libgnome-bg-4-dev":"gnome-desktop","libavutil-dev":"ffmpeg","libnetcdf-dev":"netcdf","libespeak-ng-dev":"espeak-ng","libnetfilter-log-dev":"libnetfilter_log","xserver-xephyr":"xorg-server","libfm-qt11":"libfm-qt","mailcap":"mailcap","libstemmer-dev":"libstemmer","libgtkglext1-dev":"gtkglext","libxcomposite-dev":"libXcomposite","libparmap-ocaml-dev":"parmap","ethtool":"ethtool","libsqlite3-0":"sqlite","libzen-dev":"libzen","libvted-3-dev":"gtkd","libdbd-pgsql":"libdbi-drivers","libeigen3-dev":"eigen","libice-dev":"libICE","lvm2":"lvm2","libexiv2-dev":"exiv2","netcdf-bin":"netcdf","asciidoc-base":"asciidoc","libxcvt-dev":"libxcvt","libndctl-dev":"libndctl","libgstreamermm-1.0-dev":"gstreamermm","procyon-decompiler":"procyon","iso-codes":"iso-codes","libgsasl7-dev":"gsasl","libirecovery-1.0-dev":"libirecovery","libmosquitto-dev":"mosquitto","geoclue-2.0":"geoclue","xdg-desktop-portal-dev":"xdg-desktop-portal","pidgin":"pidgin","python3-urwid":"urwid","valac":"vala","singular-data":"singular","libsdl2-image-dev":"SDL","libghc-pandoc-dev":"pandoc","libgles2":"libglvnd","python3-nbconvert":"nbconvert","libxmuu-dev":"libXmu","python3-pyside2.qtwebenginecore":"pyside2","html2text":"html2text","vdirsyncer":"vdirsyncer","libdav1d-dev":"dav1d","freerdp2-dev":"freerdp","libpeas-1.0-0":"libpeas","libgudev-1.0-dev":"libgudev","libopencryptoki-dev":"opencryptoki","python3-openssl":"pyopenssl","gir1.2-flatpak-1.0":"flatpak","python3-pydantic":"pydantic","guile-3.0-dev":"guile","librsvg2-dev":"librsvg","pidgin-dev":"pidgin","libxtables-dev":"iptables","i2c-tools":"i2c-tools","emacs-el":"emacs","gnu-efi":"gnu-efi","libgwenhywfar-core-dev":"gwenhywfar","libtotem-plparser-dev":"totem-pl-parser","libpcre2-dev":"pcre2","libxmlsec1-dev":"xmlsec","libxneur-dev":"xneur","libjsonrpc-glib-1.0-dev":"jsonrpc-glib","libnautilus-extension-dev":"nautilus","python3-pytest":"pytest","libxslt-dev":"libxslt","libcpp-hocon-dev":"cpp-hocon","libkeybinder-dev":"keybinder","libtracker-sparql-3.0-dev":"tracker","xxd":"vim","winbind":"samba","liblog4cplus-dev":"log4cplus","id3v2":"id3v2","libabw-dev":"libabw","singular-ui":"singular","libosd-dev":"opensubdiv","plasma-framework":"plasma-framework","libqaccessibilityclient-qt5-dev":"libqaccessibilityclient","liblcms2-dev":"lcms2","libcaca-dev":"libcaca","kdevelop-pg-qt":"kdevelop-pg-qt","tdb-tools":"tdb","libkf5style-dev":"frameworkintegration","libltdl-dev":"libtool","libflint-dev":"flint","libiw-dev":"wireless-tools","libois-dev":"ois","libnm-dev":"networkmanager","libslopy7.6":"slop","libgoocanvas-2.0-dev":"goocanvas","libva-dev":"libva","python3-requests":"requests","libgssdp-doc":"gssdp","file":"file","libaudiofile-dev":"audiofile","libb2-dev":"libb2","gradle":"gradle","libapr1-dev":"apr","libwnck-dev":"libwnck","libaprutil1-dev":"apr-util","libdxflib-dev":"dxflib","libhidapi-dev":"hidapi","python3-pyside2.qtcore":"pyside2","python3:any":"python","python3-ujson":"ujson","libmysofa-dev":"libmysofa","libbytesize-dev":"libbytesize","python3-mistune":"mistune","python3-dataclasses-json":"dataclasses-json","libjxl-dev":"libjxl","libqb-dev":"libqb","xcb-proto":"xcb-proto","libcdd-dev":"cddlib","qtlocation5-dev":"qtlocation","mlton":"mlton","libutf8proc-dev":"utf8proc","libtagc0-dev":"taglib","libzzip-dev":"zziplib","python3-opencv":"opencv","python3-zmq":"pyzmq","xjadeo":"xjadeo","python3-magic":"python-magic","xdg-desktop-portal":"xdg-desktop-portal","bamfdaemon":"bamf","cmake":"cmake","mat2":"mat2","zip":"zip","libsdl-gfx1.2-dev":"SDL_gfx","opencv-data":"opencv","libiec61883-dev":"libiec61883","python3-smbus":"i2c-tools","libfolks-dev":"folks","libtspi-dev":"trousers","python3-pil.imagetk":"pillow","libcairo-dev":"cairo","libsimgear-dev":"simgear","libao-dev":"libao","python3-binaryornot":"binaryornot","cups-ipp-utils":"cups","libtbb-dev":"tbb","kde-config-cddb":"libkcddb","pinentry-curses":"pinentry","libebur128-dev":"libebur128","rpm2cpio":"rpm","libsynctex-dev":"texlive-bin","libowfat0":"libowfat","qtbase5-private-dev":"qtbase","openssh-client":"openssh","libgps-dev":"gpsd","libfolks-telepathy-dev":"folks","python3-bs4":"beautifulsoup4","fish":"fish","openjdk-12-jre-headless":"openjdk","libmythes-dev":"mythes","libkf5akonadinotes-dev":"akonadi-notes","libsepol-dev":"libsepol","gnupg2":"gnupg","libopenscenegraph-3.4-dev":"openscenegraph","evolution-data-server":"evolution-data-server","qemu-block-extra":"qemu","libpspell-dev":"aspell","gawk":"gawk","samba-common":"samba","python3-networkx":"networkx","dtach":"dtach","python3-libxml2":"libxml2","qml-module-qt-labs-platform":"qtquickcontrols","gir1.2-atspi-2.0":"at-spi2-core","gir1.2-telepathyglib-0.12":"telepathy-glib","libxcb-icccm4-dev":"xcb-util-wm","python3-speechd":"speech-dispatcher","libglfw3-dev":"glfw","libmbim-glib-dev":"libmbim","libini-config-dev":"ding-libs","libdaq-dev":"daq","qtbase5-dev":"qtbase","xdg-utils":"xdg-utils","crystal":"crystal","libgsasl-dev":"gsasl","libopenslide-dev":"openslide","libstfl-dev":"stfl","libkf5contacts-dev":"kcontacts","libsuitesparse-dev":"suitesparse","unifdef":"unifdef","libfeedback-dev":"feedbackd","mesa-common-dev":"mesa","libsource-highlight-dev":"source-highlight","python3-rdflib":"rdflib","libspa-0.2-dev":"pipewire","libuecc-dev":"libuecc","libsoapysdr0.8-dev":"soapysdr","libinstpatch-dev":"libinstpatch","libgtkspell3-3-dev":"gtkspell","djview3":"djvulibre","libxcb-util0-dev":"xcb-util","libsane-dev":"sane-backends","gir1.2-vte-2.91":"vte","libntl-dev":"ntl","duktape-dev":"duktape","gitk":"git","libmbedtls-dev":"mbedtls","pyqt5-dev":"PyQt5","libghc-hscolour-prof":"hscolour","libgegl-dev":"gegl","blueprint-compiler":"blueprint-compiler","libappstream-dev":"appstream","libpolkit-qt5-1-dev":"polkit-qt-1","python3-dill":"dill","gnulib":"gnulib","mednafen":"mednafen","python3-gpg":"gpgme","dnsmasq-base":"dnsmasq","python3-toposort":"toposort","libpcaudio-dev":"pcaudiolib","jsbeautifier":"jsbeautifier","fcitx5-module-quickphrase":"fcitx5","libextractor-dev":"libextractor","gir1.2-osmgpsmap-1.0":"osm-gps-map","libkcolorpicker-dev":"kcolorpicker","libnspr4":"nspr","libnl-3-dev":"libnl","libjbig2dec0":"jbig2dec","libgraphicsmagick1-dev":"graphicsmagick","libpwquality-tools":"libpwquality","dmsetup":"lvm2","libpano13-bin":"libpano13","libmpfr-dev":"mpfr","libgd-dev":"gd","libykpers-1-dev":"yubikey-personalization","highlight":"highlight","librhash-dev":"rhash","gnuplot5-nox":"gnuplot","libell-dev":"ell","libluksmeta-dev":"luksmeta","python3-pyside2.qtwidgets":"pyside2","libbctoolbox-dev":"bctoolbox","libgpgme11-dev":"gpgme","python3-github":"PyGithub","dos2unix":"dos2unix","libfreeipmi-dev":"freeipmi","libolm-dev":"olm","python3-binwalk":"binwalk","openjdk-11-jdk":"openjdk","libgwengui-qt5-dev":"gwenhywfar","jsvc":"commons-daemon","libhamlib4":"hamlib","python3-knack":"knack","libde265-dev":"libde265","libh2o-dev":"h2o","librrd-dev":"rrdtool","python3-pyaes":"pyaes","libkf5doctools-dev":"kdoctools","swig":"swig","libg15render-dev":"libg15render","libpixman-1-dev":"pixman","gnunet":"gnunet","zeitgeist":"zeitgeist","libinklevel-dev":"libinklevel","libnspr4-dev":"nspr","python3-rfc3339":"pyRFC3339","libktorrent-dev":"libktorrent","raptor2-utils":"raptor2","libvirt-glib-1.0-dev":"libvirt-glib","libpcap0.8-dev":"libpcap","singular-modules":"singular","libfreetype-dev":"freetype","libspectre-dev":"libspectre","x11proto-core-dev":"xorgproto","python3-gvm":"python-gvm","libkf5su-dev":"kdesu","checkpolicy":"checkpolicy","wx3.0-headers":"wxwidgets","libclang-dev":"clang","gwenhywfar-tools":"gwenhywfar","libsynfig-dev":"synfig","libqwt-headers":"qwt","librust-libc-0.2-dev":"rustc","libwacom-dev":"libwacom","plasma-wayland-protocols":"plasma-wayland-protocols","libopenipmi-dev":"OpenIPMI","luajit":"luajit","libkf5baloowidgets-dev":"baloo-widgets","libplot-dev":"plotutils","libkf5plasma-dev":"plasma-framework","libfolia-dev":"libfolia","libcryptokit-ocaml-dev":"cryptokit","libgtk-3-bin":"gtk+","libpaper-dev":"libpaper","libkf5runner-dev":"krunner","xnee":"xnee","libxmlb-dev":"libxmlb","liblua5.2-dev":"lua","poppler-utils":"poppler-utils","lib3mf-dev":"lib3mf","dleyna-renderer":"dleyna-renderer","evolution-dev":"evolution","okular":"okular","acl":"acl","libkf5ldap-dev":"kldap","colord":"colord","exiv2":"exiv2","libneatvnc-dev":"neatvnc","imagemagick":"imagemagick","gperf":"gperf","libxext-dev":"libXext","libcunit1-dev":"CUnit","libopenvdb-tools":"openvdb","libxxf86vm-dev":"libXxf86vm","libfarstream-0.2-dev":"farstream","gnunet-dev":"gnunet","libparmap-ocaml":"parmap","gir1.2-wnck-3.0":"libwnck","libnpth0-dev":"npth","libudfread-dev":"libudfread","libuid-wrapper":"uid_wrapper","libgivaro-dev":"givaro","libxcb-ewmh-dev":"xcb-util-wm","liblz4-tool":"lz4","libijs-dev":"ijs","libkf5xmlgui-dev":"kxmlgui","libgupnp-av-1.0-dev":"gupnp-av","libgrpc++-dev":"grpc","liblaszip-dev":"LASzip","libkf5kontactinterface-dev":"kontactinterface","qemu-system-misc":"qemu","ocaml-base":"ocaml","numad":"numad","gir1.2-gtkspell3-3.0":"gtkspell","libpano13-dev":"libpano13","libxtst-dev":"libXtst","unixodbc-dev":"unixODBC","libjpeg62-turbo-dev":"libjpeg-turbo","libshout-dev":"libshout","libuhttpmock-0.0-dev":"uhttpmock","python3-javaproperties":"javaproperties","psmisc":"psmisc","libimagequant-dev":"libimagequant","cups-filters":"cups-filters","bison":"bison","libkf5iconthemes-dev":"kiconthemes","libg15-1":"libg15","qml-module-org-kde-draganddrop":"kdeclarative","libluajit-5.1-dev":"luajit","libnfc-dev":"libnfc","gir1.2-gdkpixbuf-2.0":"gdk-pixbuf","libgda-5.0-postgres":"libgda","libopenscenegraph-dev":"openscenegraph","mlton-tools":"mlton","libarchive-dev":"libarchive","libcotp-dev":"libcotp","libgtksourceview-3.0-dev":"gtksourceview","libbluray-dev":"libbluray","scons":"scons","libunwind8-dev":"libunwind","libimath-dev":"imath","libytnef-dev":"libytnef","libaom-dev":"libaom","openvpn":"openvpn","python3-cairo":"pycairo","libfakekey-dev":"libfakekey","libinput-dev":"libinput","w3m":"w3m","libode-dev":"ode","ant-optional":"ant","python3-pyqt5.qtmultimedia":"PyQt5","bash-completion":"bash-completion","libucommon-dev":"ucommon","python3-configobj":"configobj","libdleyna-core-1.0-dev":"dleyna-core","rust-gdb":"rustc","mono-devel":"mono","librsync-dev":"librsync","libxcb-keysyms1-dev":"xcb-util-keysyms","tasty-discover":"tasty-discover","clang-13":"clang","libstd-rust-dev-wasm32":"rustc","libayatana-indicator3-dev":"libayatana-indicator","libhdf5-openmpi-dev":"hdf5","notmuch":"notmuch","perl-doc":"perl","python3-mako":"Mako","libuchardet-dev":"uchardet","mplayer":"mplayer","bind9-host":"bind","python3-pyudev":"pyudev","libcjson1":"cjson","llvm-6.0-dev":"llvm","python3-opengl":"pyopengl","remind":"remind","llvm-15-dev":"llvm","rustfmt":"rustc","python3-brotli":"brotli","librasqal3-dev":"rasqal","libgda-5.0-mysql":"libgda","python3-pendulum":"pendulum","libxv-dev":"libXv","librange-v3-dev":"range-v3","libegl1":"libglvnd","libenchant-2-2":"enchant","check":"check","lzip":"lzip","python3-dateutil":"python-dateutil","python3-levenshtein":"python-levenshtein","libpulse-dev":"pulseaudio","intltool":"intltool","libgles-dev":"libglvnd","libopenimageio-dev":"openimageio","libcryptsetup-dev":"cryptsetup","sbcl":"sbcl","python3-pyqt5.qtsql":"PyQt5","libncurses6":"ncurses","libb64-dev":"libb64","dconf-cli":"dconf","gstreamer1.0-tools":"gstreamer","libgtkextra-dev":"gtkextra","libmicrohttpd-dev":"libmicrohttpd","libflatpak-dev":"flatpak","libvpx-dev":"libvpx","libsdl-mixer1.2-dev":"SDL_mixer","libqwt-dev":"qwt","bluez-obexd":"bluez","libserd-dev":"serd","wx3.0-i18n":"wxwidgets","libuim-dev":"uim","gengetopt":"gengetopt","python3-sip-dev":"sip","libidn11-dev":"libidn","libserialport-dev":"libserialport","python3-pyatspi":"pyatspi","libfontconfig-dev":"fontconfig","graphicsmagick-imagemagick-compat":"graphicsmagick","cups":"cups","python3-cfgv":"cfgv","python3-patatt":"patatt","libhdf5-mpich-dev":"hdf5","libmagickcore-6.q16-6-extra":"imagemagick","libusbredirhost1":"usbredir","vorbisgain":"vorbisgain","libbabeltrace-dev":"babeltrace","libkreport3-dev":"kreport","qml-module-org-kde-kirigami2":"kirigami2","tpm2-tools":"tpm2-tools","libkf5crash-dev":"kcrash","libmm-glib-dev":"modemmanager","libcomedi-dev":"comedilib","libxinerama1":"libXinerama","libxinerama-dev":"libXinerama","wordnet":"wordnet","qml-module-org-kde-qqc2desktopstyle":"qqc2-desktop-style","libslang2-dev":"slang","openssl":"openssl","libmpd-dev":"libmpd","libappstream-glib-dev":"appstream-glib","emacs25-lucid":"emacs","libmongoc-dev":"mongoc","python3-pytest-mock":"pytest-mock","qtxmlpatterns5-dev-tools":"qtxmlpatterns","libxkbfile-dev":"libxkbfile","libhtmlcxx-dev":"htmlcxx","libdevhelp-dev":"devhelp","triehash":"triehash","xfsprogs":"xfsprogs","libjose-dev":"jose","libtalloc-dev":"talloc","python3-hatch-vcs":"hatch-vcs","gnuplot":"gnuplot","libfaad-dev":"faad2","iproute2":"iproute2","dirmngr":"gnupg","libqt5charts5-dev":"qt","audacious":"audacious","libbaseencode-dev":"libbaseencode","libqpdf-dev":"qpdf","librandomx-dev":"randomX","libogg-dev":"libogg","mlton-runtime-native":"mlton","python3-pydbus":"pydbus","libpsm2-dev":"libpsm2","libgdl-3-dev":"gdl","gir1.2-gtk-2.0":"gtk+","libbtrfs-dev":"btrfs-progs","libneon-dev":"neon","libagg-dev":"agg","libgl-dev":"libGL","hwloc-nox":"hwloc","libfs-dev":"libFS","libkf5jobwidgets-dev":"kjobwidgets","llvm-dev":"llvm","python3-pyte":"pyte","libunistring-dev":"libunistring","snapper":"snapper","modemmanager":"modemmanager","libghc-pandoc-prof":"pandoc","libcolord-dev":"colord","liblo-dev":"liblo","libudunits2-dev":"udunits","dodgy":"dodgy","libstd-rust-1.64":"rustc","libkf5package-dev":"kpackage","ruby3.1":"ruby","libfltk1.1-dev":"fltk","gir1.2-gtk-vnc-2.0":"gtk-vnc","libkf5qqc2desktopstyle-dev":"qqc2-desktop-style","python3-poetry-core":"poetry-core","libsrt-gnutls-dev":"srt","libxkbcommon-dev":"libxkbcommon","accountsservice":"accountsservice","libopenblas-base":"openblas","info":"texinfo","libosp-dev":"opensp","libhttrack-dev":"httrack","libblas-dev":"blas","python3-platformdirs":"platformdirs","libcolord-gtk-dev":"colord-gtk","libfplll-dev":"fplll","icon-naming-utils":"icon-naming-utils","fp-units-fcl":"fpc","libavahi-common-dev":"avahi","whois":"whois","python3-ripe-atlas-sagan":"ripe-atlas-sagan","libgssdp-1.6-0":"gssdp","llvm":"llvm","ldc":"ldc","python3-savitar":"libsavitar","libwaffle-dev":"waffle","libsingular4-dev":"singular","djvulibre-desktop":"djvulibre","libsm-dev":"libSM","libkf5itemmodels-dev":"kitemmodels","python3-sshtunnel":"sshtunnel","libopencolorio-dev":"opencolorio","gir1.2-gtk-3.0":"gtk+","goobook":"goobook","libaal-dev":"libaal","gir1.2-soup-2.4":"libsoup","libgsm1-dev":"gsm","python3-duecredit":"duecredit","python3-brlapi":"brltty","evolution-data-server-dev":"evolution-data-server","libre-dev":"libre","libproxy-dev":"libproxy","liboggz2-dev":"liboggz","libnatpmp-dev":"libnatpmp","phosh":"phosh","fp-units-net":"fpc","libfastjson-dev":"fastjson","libcfg-dev":"corosync","libzip-ocaml-dev":"camlzip","libblockdev-dev":"libblockdev","python3-gnupg":"python-gnupg","libxc-dev":"libxc","libminizip-dev":"minizip","liblognorm-dev":"liblognorm","heimdal-clients":"heimdal","libsndfile-dev":"libsndfile","flac":"flac","libsope-dev":"sope","iputils-ping":"iputils","libcogl-dev":"cogl","libcanberra-gtk3-dev":"libcanberra","fcitx5":"fcitx5","python3-aiohttp-socks":"aiohttp-socks","libsmf-dev":"libsmf","git":"git","libcamel1.2-dev":"evolution-data-server","python3-xdg":"pyxdg","libstellarsolver-dev":"stellarsolver","libkf5calendarutils-dev":"kcalutils","cryptsetup-bin":"cryptsetup","feedbackd":"feedbackd","ucto":"ucto","network-manager":"networkmanager","python3-poppler-qt5":"python-poppler-qt5","libdv4-dev":"libdv","libacl1-dev":"acl","libseccomp-dev":"libseccomp","kdepim-addons":"kdepim-addons","python3-three-merge":"three-merge","pcscd":"pcsclite","libkf5akonadicontact-dev":"akonadi-contacts","pass":"password-store","gtk-update-icon-cache":"gtk+","gstreamer1.0-lame":"gstreamer","libluajit2-5.1-dev":"luajit","opensp":"opensp","libblockdev-kbd-dev":"libblockdev","libgl1":"libglvnd","libczmq-dev":"czmq","libvirt-clients":"libvirt","python3-paramiko":"paramiko","libopenmpt-dev":"libopenmpt","libibverbs-dev":"rdma-core","libgnunet-dev":"gnunet","libgpiod-dev":"libgpiod","liboath-dev":"oath-toolkit","libxcb-shm0-dev":"libxcb","cxxtest":"cxxtest","libwmf-dev":"libwmf","libcurl4-openssl-dev":"curl","libfstrcmp-dev":"fstrcmp","libgcr-3-dev":"gcr","libbulletml-dev":"bulletml","python3-sphinx-rtd-theme":"sphinx-rtd-theme","swh-plugins":"swh-plugins","perl-base":"perl","libh2o-evloop-dev":"h2o","libdjvulibre-dev":"djvulibre","fp-utils":"fpc","libgpg-error-dev":"libgpg-error","gdb":"gdb","libusbmuxd-dev":"libusbmuxd","groff":"groff","python3-gensio":"gensio","libvala-dev":"vala","python3-send2trash":"Send2Trash","libstd-rust-1.63":"rustc","libfltk-dev":"fltk","libcoin-dev":"coin","sqlite3":"sqlite","libgusb-dev":"gusb","python3-textdistance":"textdistance","libfcitx5config-dev":"fcitx5","python3-hatchling":"hatchling","libprimesieve-dev":"primesieve","libxcb-imdkit-dev":"xcb-imdkit","python3-html5-parser":"html5-parser","yt-dlp":"yt-dlp","libaccountsservice-dev":"accountsservice","pim-data-exporter":"pim-data-exporter","python3-pikepdf":"pikepdf","python3-dbusmock":"python-dbusmock","libavfilter-dev":"ffmpeg","python3-img2pdf":"img2pdf","libgme-dev":"game-music-emu","libopenexr-dev":"openexr","wordnet-sense-index":"wordnet","libcodec2-dev":"codec2","libxpm-dev":"libXpm","vorbis-tools":"vorbis-tools","python3-uranium":"uranium","fontforge":"fontforge","libnss3-dev":"nss","libfuse-dev":"fuse","libhangul-data":"libhangul","libkf5sysguard-dev":"libksysguard","libzip-dev":"libzip","libumockdev-dev":"umockdev","libgraphviz-dev":"graphviz","libxapp-dev":"xapp","snmpd":"net-snmp","bogofilter":"bogofilter","zlib1g":"zlib","kio":"kio","libproperties-cpp-dev":"properties-cpp","guile":"guile","python3-pypdf2":"PyPDF2","kwin":"kwin","libopencc-dev":"opencc","rpm":"rpm","libchromaprint-dev":"chromaprint","kinit-dev":"kinit","gir1.2-notify-0.7":"libnotify","libgssdp-1.6-dev":"gssdp","libnetfilter-queue-dev":"libnetfilter_queue","libchamplain-0.12-dev":"libchamplain","python3-numpydoc":"numpydoc","lib3ds-dev":"lib3ds","libgtk-4-dev":"gtk4","lilypond-doc":"lilypond","connman":"connman","libncurses5-dev:native":"ncurses","audacious-dev":"audacious","libtelepathy-glib-dev":"telepathy-glib","libtracecmd-dev":"trace-cmd","libpystring-dev":"pystring","python3-rpm":"rpm","gstreamer1.0-plugins-really-bad":"gstreamer","elixir":"elixir","gir1.2-rsvg-2.0":"librsvg","oggvideotools":"oggvideotools","ldap-utils":"openldap","fdisk":"util-linux","libxdg-basedir-dev":"libxdg-basedir","libnfs-dev":"libnfs","lemon":"lemon","pinentry":"pinentry","libgpgmepp-dev":"gpgme","libsoxr-dev":"soxr","cd-paranoia":"libcdio-paranoia","gnutls-dev":"gnutls","libgpm-dev":"gpm","libilmbase-dev":"ilmbase","gstreamer1.0-nice":"gstreamer","python3-podcastparser":"podcastparser","docbook2x":"docbook2X","python3-portalocker":"portalocker","libdatrie-dev":"libdatrie","libraw1394-dev":"libraw1394","libnetpbm-dev":"netpbm","opencl-headers":"opencl-headers","libxcb-present-dev":"libxcb","libtinygltf-dev":"tinygltf","xneur":"xneur","python3-qt5reactor":"qt5reactor","libxrandr2":"libXrandr","libcpuid-dev":"libcpuid","androguard":"androguard","qtfeedback5-dev":"qtfeedback","opencryptoki":"opencryptoki","libiptc-dev":"iptables","qtscript5-dev":"qtscript","libspiro-dev":"libspiro","dnsutils":"bind","libwildmidi-dev":"wildmidi","libkf5codecs-dev":"kcodecs","samba-dev":"samba","ladspa-sdk":"ladspa-sdk","libsundials-dev":"sundials","openssh-server":"openssh","libaqbanking-dev":"aqbanking","libkf5syndication-dev":"syndication","libatasmart-dev":"libatasmart","librevenge-dev":"librevenge","libkf5config-dev":"kconfig","systemd":"systemd","libopenblas64-openmp-dev":"openblas","libonig-dev":"onig","routino":"routino","cdrdao":"cdrdao","fcitx5-modules-dev":"fcitx5","autoconf-archive":"autoconf-archive","libpci-dev":"pciutils","emacs24-lucid":"emacs","libgdk-pixbuf2.0-doc":"gdk-pixbuf","sng":"sng","cracklib-runtime":"cracklib","libssl1.0-dev":"openssl","libguestfs-perl":"libguestfs","varnish":"varnish","python3-yaml":"pyyaml","dpkg-dev":"dpkg","libevdev-dev":"libevdev","python3-pylint-django":"pylint-django","libzimg-dev":"zimg","pulseaudio":"pulseaudio","libedit-dev":"libedit","libcfitsio-dev":"cfitsio","python3-pymacaroons":"pymacaroons","python3-defusedxml":"defusedxml","tracker":"tracker","libgnome-autoar-0-dev":"gnome-autoar","libzita-alsa-pcmi-dev":"zita-alsa-pcmi","lz4":"lz4","libc-client2007e-dev":"uw-imap","libqmi-glib-dev":"libqmi","libgirepository1.0-dev":"gobject-introspection","libhamlib-dev":"hamlib","libintl-perl":"libintl-perl","kleopatra":"kleopatra","libsymspg-dev":"spglib","libayatana-ido3-dev":"ayatana-ido","libusbredirparser1":"usbredir","librtmidi-dev":"rtmidi","libfcitx5utils-dev":"fcitx5","libaubio-dev":"aubio","alsa-utils":"alsa-utils","pgpdump":"pgpdump","libkf5windowsystem-dev":"kwindowsystem","libdvdnav-dev":"libdvdnav","melt":"mlt","libgpgme-dev":"gpgme","python3-psycopg2":"psycopg2","libblockdev-fs-dev":"libblockdev","libofx-dev":"libofx","libvamp-sdk2v5":"vamp-plugin-sdk","autopoint":"gettext","libzita-convolver-dev":"zita-convolver","python3-fabric":"fabric","libbelcard-dev":"belcard","python3-six":"six","libsystemd-dev":"systemd","libinih-dev":"inih","libjansson4":"jansson","libewf-dev":"libewf","libopendht-dev":"opendht","x11proto-gl-dev":"xorgproto","libswscale-dev":"ffmpeg","libncurses5-dev":"ncurses","kwin-dev":"kwin","rsync":"rsync","libtokyocabinet-dev":"tokyocabinet","qtwayland5":"qtwayland","libvkd3d-dev":"vkd3d","python3-pyqtbuild":"pyqt-builder","libedata-book1.2-dev":"evolution-data-server","luksmeta":"luksmeta","libtcl":"tcl","libglew1.6-dev":"glew","python3-pycodestyle":"pycodestyle","libpinyin-common-dev":"libpinyin","lsof":"lsof","libgtk-3-dev":"gtk+","liblua5.1-0-dev":"lua","libperl-dev":"perl","libaio1":"libaio","libkf5su-bin":"kdesu","libyajl-dev":"yajl","libxft2-dev":"libXft","kwin-wayland":"kwin","qml-module-org-kde-kcmutils":"kcmutils","libgoocanvasmm-2.0-dev":"goocanvasmm","libfreexl-dev":"freexl","libdmtx-dev":"libdmtx","libgupnp-igd-1.0-dev":"gupnp-igd","libcrypto++-dev":"crypto++","python-gi-dev":"pygobject","libscrypt-dev":"libscrypt","libtracefs-dev":"libtracefs","libdbd-mysql":"libdbi-drivers","libsoup-gnome2.4-dev":"libsoup","librelp-dev":"librelp","libsystemd0":"systemd","libgnome-games-support-1-dev":"libgnome-games-support","libgetdns10":"getdns","libsoup2.4-dev":"libsoup","libkf5cddb-dev":"libkcddb","ruby3.1-dev":"ruby","libkf5mediaplayer-dev":"kmediaplayer","libmp3splt":"libmp3splt","libsgutils2-dev":"sg3_utils","libpam-systemd":"systemd","libusbredirparser-dev":"usbredir","libprotobuf-c-dev":"protobuf-c","qemu-system-data":"qemu","gstreamer1.0-plugins-base":"gstreamer","libt4k-common0-dev":"t4kcommon","libp8-platform-dev":"p8-platform","libcanberra-dev":"libcanberra","libntirpc-dev":"ntirpc","libopenobex2-dev":"openobex","gir1.2-gssdp-1.2":"gssdp","auditd":"audit","libtiff4-dev":"libtiff","librsvg2-2":"librsvg","python3-sortedcontainers":"sortedcontainers","libportal-gtk4-dev":"libportal-gtk4","libavahi-client-dev":"avahi","librust-libc-dev":"rustc","libgbm-dev":"mesa","tcl8.7":"tcl","plasma-workspace-dev":"plasma-workspace","gir1.2-gstreamer-1.0":"gstreamer","libllvm-":"llvm","pari-gp":"pari","libapparmor1":"libapparmor","qtbase5-dev-tools":"qtbase","libasyncns-dev":"libasyncns","python3-protobuf":"protobuf","libzmq3-dev":"zeromq","libdvdcss-dev":"libdvdcss","vcdimager":"vcdimager","libcap-ng-dev":"libcap-ng","lua5.3":"lua","libexif-dev":"libexif","python3-typer":"typer","libxcb-shape0-dev":"libxcb","libeditreadline-dev":"libedit","python3-pyqt5":"PyQt5","clang":"clang","sphinx":"sphinx","libcsxcad0":"csxcad","libaa1-dev":"aalib","libkf5khtml-dev":"khtml","anthy":"anthy","python3-construct":"construct","libffi-dev":"libffi","p7zip":"p7zip","libe-book-dev":"libe-book","libxcb-glx0-dev":"libxcb","xbrlapi":"brltty","libtspi1":"trousers","libcpg-dev":"corosync","python3-webtest":"webtest","libspice-protocol-dev":"spice-protocol","libeccodes-dev":"eccodes","puredata":"puredata","libunibilium-dev":"unibilium","libvirt-ocaml":"ocaml-libvirt","python3-gdal":"gdal","librpm-dev":"rpm","libgl2ps-dev":"gl2ps","libguestfs-ocaml-dev":"libguestfs","libkf5dbusaddons-dev":"kdbusaddons","jose":"jose","libopenjp2-7-dev":"openjpeg","libkf5plasma5":"plasma-framework","libdw1":"elfutils","mtools":"mtools","libpcap-dev":"libpcap","libsdl2-ttf-dev":"SDL","python3-nose":"nose","plplot-driver-wxwidgets":"plplot","libgpgme11":"gpgme","libcairomm-1.0-dev":"cairomm","dbus-user-session":"dbus","python3-sqlalchemy":"SQLAlchemy","ncurses-term":"ncurses","qtquickcontrols2-5-dev":"qtquickcontrols","libdw-dev":"elfutils","libblockdev-fs2":"libblockdev","libsbc-dev":"sbc","libbson-dev":"libbson","libqrupdate-dev":"qrupdate","libzstd-dev":"zstd","libcurl2-dev":"curl","lm-sensors":"lm-sensors","libtdb-dev":"tdb","libchm-dev":"chmlib","libavahi-gobject-dev":"avahi","corosync":"corosync","python3-debian":"python-debian","python3-guestfs":"guestfs","gir1.2-spiceclientglib-2.0":"spice-gtk","libgtkmm-3.0-dev":"gtkmm","libgtksourceview-4-dev":"gtksourceview","usbutils":"usbutils","libnl-nf-3-dev":"libnl","libconfig++-dev":"libconfig","libbamf3-dev":"bamf","libgensio-dev":"gensio","lxqt-build-tools":"lxqt-build-tools","gstreamer1.0-videosink":"gstreamer","libgeoip-dev":"geoip","libcifpp-dev":"libcifpp","sudo":"sudo","gir1.2-jsonrpc-1.0":"jsonrpc-glib","libtiff-dev":"libtiff","faad":"faad2","libcurses-ocaml":"ocaml-curses","python3-jwt":"pyjwt","libxcb-render0-dev":"libxcb","librem-dev":"librem","libzxingcore-dev":"zxing-cpp","libcairo2-dev":"cairo","libfribidi-dev":"fribidi","libfluidsynth-dev":"fluidsynth","libgnustep-base-dev":"gnustep-base","libdazzle-1.0-dev":"libdazzle","kpeople-vcard":"kpeoplevcard","libmediainfo-dev":"libmediainfo","libvte-2.91-0":"vte","libgxps-dev":"libgxps","gnuradio-dev":"gnuradio","mypy":"mypy","libqhull-dev":"qhull","m17n-db":"m17n-db","libcamomile-ocaml-data":"camomile","python3-cdio":"pycdio","qcoro-qt5-dev":"qcoro","pulseaudio-module-zeroconf":"pulseaudio","mlton-compiler":"mlton","guile-2.2-dev":"guile","python3-parsedatetime":"parsedatetime","python3-pyinotify":"pyinotify","glib-networking":"glib-networking","debugedit":"debugedit","ronn":"ronn","libgl1-mesa-dev":"mesa","libvorbisenc2":"libvorbis","libgspell-1-dev":"gspell","libxdamage-dev":"libXdamage","libmikmod-dev":"libmikmod","libflatbuffers-dev":"flatbuffers","python3-twisted":"twisted","libmagickcore-dev":"imagemagick","install-info":"texinfo","libaugeas-dev":"augeas","libipt-dev":"libipt","libkf5akonadi-dev":"akonadi","libdvdread-dev":"libdvdread","libsidplayfp-dev":"libsidplayfp","ruby-dev":"ruby","libepoxy-dev":"libepoxy","python3-pyfuse3-dbg":"pyfuse3","libliquid-dev":"liquid-dsp","python3-pydot":"pydot","libjson-c-dev":"json-c","libgraphene-1.0-dev":"graphene","llvm-14-tools:native":"llvm","libimepinyin-dev":"libime","gir1.2-secret-1":"libsecret","clasp":"clasp","libkf5akonadisearch-dev":"akonadi-search","odt2txt":"odt2txt","jq":"jq","yelp-tools":"yelp-tools","libkmod-dev":"kmod","lilypond":"lilypond","python3-feedparser":"feedparser","scdaemon":"gnupg","pyflakes3":"pyflakes","libebackend1.2-dev":"evolution-data-server","txt2man":"txt2man","nettle-dev":"nettle","flam3-palette":"flam3","libmygui-dev":"mygui","gir1.2-soup-3.0":"libsoup","mandoc":"mandoc","libiberty-dev":"libiberty","gir1.2-farstream-0.2":"farstream","gir1.2-gudev-1.0":"libgudev","pdftk":"pdftk","libalure-dev":"alure","libmenu-cache-dev":"menu-cache","libltc-dev":"libltc","emacs24":"emacs","libudns-dev":"udns","libcurl4-dev":"curl","vtable-dumper":"vtable-dumper","gnutls-bin":"gnutls","ocaml-base-nox":"ocaml","libxrandr-dev":"libXrandr","emacs":"emacs","liblmdb-dev":"lmdb","libsndfile1-dev":"libsndfile","python3-pytest-runner":"pytest-runner","libslopy-dev":"slop","libpangomm-1.4-dev":"pangomm","libgringotts-dev":"libgringotts","ncurses-dev":"ncurses","slsh":"slang","caca-utils":"libcaca","libwebp-dev":"libwebp","libmcrypt-dev":"libmcrypt","libopus-dev":"libopus","libflam3-dev":"flam3","rapidjson-dev":"rapidjson","gstreamer1.0-audiosink":"gstreamer","xfce4-dev-tools":"xfce4-dev-tools","gnuplot5-x11":"gnuplot","libgdk-pixbuf-2.0-0":"gdk-pixbuf","libsdl2-dev":"SDL","python3-stevedore":"stevedore","libnova-dev":"libnova","qml-module-org-kde-bluezqt":"bluez-qt","python3-gitlab":"python-gitlab","liblirc-dev":"lirc","libxml2-utils":"libxml2","tk":"tk","libruby":"ruby","par2":"par2cmdline","libxpm4":"libXpm","libcrack2-dev":"cracklib","libkpmcore-dev":"kpmcore","libjudy-dev":"judy","libhpdf-dev":"libharu","libsord-dev":"sord","libgexiv2-dev":"gexiv2","libvtk9-dev":"vtk","libfm-modules":"libfm","libexpat-dev":"expat","python3-scipy":"scipy","libgsl-dev":"gsl","librtaudio-dev":"rtaudio","rdiff":"librsync","libgsl0-dev":"gsl","libgcab-dev":"gcab","pyside2-tools":"pyside2-tools","libwxgtk3.0-dev":"wxwidgets","crystal-samples":"crystal","bzip2":"bzip2","libsignal-protocol-c-dev":"libsignal-protocol-c","qml-module-org-kde-newstuff":"knewstuff","etl-dev":"ETL","libtpms0":"libtpms","optipng":"optipng","dbus-x11":"dbus","libunarr-dev":"libunarr","libuhd-dev":"uhd","libpodofo-dev":"podofo","gcr":"gcr","systemd-sysv":"systemd","libconfuse-dev":"libconfuse","keyutils":"keyutils","libkf5parts-dev":"kparts","acpica-tools":"acpica-tools","guile-2.0-dev":"guile","libgrantlee5-dev":"grantlee","libidl-dev":"libIDL","libticonv-dev":"libticonv","libcdio-paranoia-dev":"libcdio-paranoia","libfprint-2-dev":"libfprint","libxnvctrl-dev":"libXNVCtrl","libio-stringy-perl":"IO-Stringy","libblockdev-kbd2":"libblockdev","libclang-15-dev":"clang","nlohmann-json3-dev":"nlohmann_json","libnfnetlink-dev":"libnfnetlink","libmagickwand-dev":"imagemagick","libkf5service-dev":"kservice","python3-blinker":"blinker","libwpebackend-fdo-1.0-dev":"wpebackend-fdo","libgucharmap-2-90-dev":"gucharmap","libsdl-sound1.2-dev":"SDL_sound","libsctp-dev":"lksctp-tools","accountwizard":"kmail-account-wizard","libtermkey-dev":"libtermkey","libxxhash-dev":"xxHash","libgnutls28-dev":"gnutls","gnome-session-bin":"gnome-session","fpc":"fpc","libflac++-dev":"flac","libnlopt-cxx-dev":"nlopt","libglibmm-2.68-dev":"glibmm","python3-notmuch2":"notmuch","fp-units-misc":"fpc","libsigrokdecode-dev":"libsigrokdecode","gnome-common":"gnome-common","libnxml0-dev":"libnxml","opus-tools":"opus-tools","git-core":"git","swi-prolog-nox":"swi-prolog","libxcb-dri3-dev":"libxcb","giflib-tools":"giflib","libkf5notifications-dev":"knotifications","libstb-dev":"stb","libglib2.0-dev":"glib","liblrs-dev":"lrs","librecode-dev":"recode","libvtk7-qt-dev":"vtk","python3-acoustid":"pyacoustid","libgnomecanvas2-dev":"libgnomecanvas","libkate-dev":"libkate","qttools5-dev-tools":"qttools","petsc-dev":"petsc","libqwt-qt5-6":"qwt","modemmanager-dev":"modemmanager","libvolume-key-dev":"volume_key","kded5":"kded","udev":"systemd","libtelepathy-farstream-dev":"telepathy-farstream","libghc-hslogger-prof":"hslogger","libxcb-xinerama0-dev":"libxcb","antlr":"antlr","plasma-workspace":"plasma-workspace","liblapack-doc":"lapack","libgirepository-1.0-1":"gobject-introspection","libswresample-dev":"ffmpeg","libembree-dev":"embree","libloudmouth1-dev":"loudmouth","libavif-dev":"libavif","python3-google-i18n-address":"google-i18n-address","libopenvdb-dev":"openvdb","openjdk-13-jre-headless":"openjdk","libtinyxml-dev":"tinyxml","ddccontrol-db":"ddccontrol-db","libcurl4-gnutls-dev":"curl","librust-libc-0.2+default-dev":"rustc","libdatrie1-bin":"libdatrie","supercollider-server":"supercollider","wmctrl":"wmctrl","libmecab-dev":"mecab","python3-rich":"rich","python3-psycopg3":"psycopg","uthash-dev":"uthash","mpv":"mpv","libmxml-dev":"mxml","ghp-import":"ghp-import","libtecla-dev":"tecla","qemu-system-common":"qemu","python3-chm":"pychm","python3-guzzle-sphinx-theme":"guzzle_sphinx_theme","libxkbregistry-dev":"libxkbcommon","libxcb-dri2-0-dev":"libxcb","pybind11-dev":"pybind11","libqwt-qt5-dev":"qwt","libcommons-daemon-java":"commons-daemon","vulture":"vulture","libelf-dev":"libelf","uranium-plugins":"uranium","libmimalloc-dev":"mimalloc","libxmu-dev":"libXmu","libcgal-qt5-dev":"cgal","tre-agrep":"tre","libgeoclue-2-dev":"geoclue","kwin-x11":"kwin","gir1.2-ggit-1.0":"libgit2-glib","dbus-system-bus-common":"dbus","libreadline-dev":"readline","synfig":"synfig","liblircclient-dev":"lirc","libtraceevent1-plugin":"libtraceevent","libprotoc-dev":"protobuf","libm17n-dev":"m17n-lib","texinfo":"texinfo","graphviz":"graphviz","ppp-dev":"ppp","python3-mypy":"mypy","libbellesip-dev":"belle-sip","libgtk-4-bin":"gtk4","python3-tdb":"tdb","re2c":"re2c","python3-pylast":"pylast","lua5.2":"lua","libqrtr-glib-dev":"libqrtr-glib","espeak-ng-data-udeb":"espeak-ng","python3-importlib-resources":"importlib-resources","libanthy-dev":"anthy","libkf5pulseaudioqt-dev":"pulseaudio-qt","libx86-dev":"libx86","libspeexdsp-dev":"speexdsp","libwayland-dev":"wayland","libblockdev-swap-dev":"libblockdev","libavahi-compat-libdnssd-dev":"avahi","zeitgeist-core":"zeitgeist","zsh":"zsh","libkf5holidays-dev":"kholidays","yamllint":"yamllint","bc":"bc","libopencv-core-dev":"opencv","python3-qdarkstyle":"qdarkstyle","gpg-agent":"gnupg","python3-peewee":"peewee","liburiparser-dev":"uriparser","libeb16-dev":"libeb","presage":"presage","libftdi-dev":"libftdi","libsamplerate0-dev":"libsamplerate","libvisio-dev":"libvisio","sassc":"sassc","libgpod-dev":"libgpod","cbindgen":"rust-cbindgen","db5.3-util":"db","libffmpegthumbnailer-dev":"ffmpegthumbnailer","libvulkan1":"vulkan-loader","libobexftp0-dev":"obexftp","libwxgtk3.2-dev":"wxwidgets","libpciaccess-dev":"libpciaccess","libcallaudio-dev":"callaudiod","firebird-dev":"firebird","libapparmor-dev":"libapparmor","libddcutil-dev":"ddcutil","libxcb-util-dev":"xcb-util","libtpms-dev":"libtpms","libre2-dev":"re2","libjpeg-dev":"libjpeg-turbo","libgda-5.0-dev":"libgda","libarmadillo-dev":"armadillo","mlton-basis":"mlton","libnice-dev":"libnice","libsfml-dev":"sfml","libgssdp-1.2-0":"gssdp","libyubikey-dev":"libyubikey","libldb-dev":"ldb","xterm":"xterm","gir1.2-gexiv2-0.10":"gexiv2","python3-virtualenv-clone":"virtualenv-clone","libad9361-dev":"libad9361","opencollada-dev":"opencollada","gir1.2-gssdp-1.6":"gssdp","libodfgen-dev":"libodfgen","libqrencode-dev":"qrencode","libcurl4":"curl","python3-setuptools":"setuptools","iptables":"iptables","mousetweaks":"mousetweaks","llvm-14-dev:native":"llvm","tcl8.7-doc":"tcl","libblockdev-mdraid2":"libblockdev","gir1.2-gtksource-4":"gtksourceview","libnghttp2-dev":"nghttp2","libtag1-dev":"taglib","libvorbis-dev":"libvorbis","libedataserver1.2-dev":"evolution-data-server","openjdk-14-jre-headless":"openjdk","libotr2-dev":"libotr","libtllist-dev":"tllist","cups-client":"cups","libargon2-dev":"libargon2","libshiboken2-dev":"pyside2","libgjs-dev":"gjs","libxaw-dev":"libXaw","libcanberra0":"libcanberra","python3-aiodns":"aiodns","e2fslibs-dev":"e2fsprogs","libfparser-dev":"fparser","tracker-extract":"tracker-miners","libpam-wrapper":"libpam-wrapper","fp-units-db":"fpc","cryptsetup":"cryptsetup","surf":"surf","qml-module-org-kde-kholidays":"kholidays","libgdata-dev":"libgdata","libtesseract-dev":"tesseract","libfreetype6-dev":"freetype","libkf5bluezqt-dev":"bluez-qt","libkf5pimtextedit-dev":"kpimtextedit","libsoundtouch-dev":"soundtouch","libxcb-sync-dev":"libxcb","libwxbase3.0-dev":"wxwidgets","python3-dbus.mainloop.pyqt5":"PyQt5","libgles2-mesa-dev":"mesa","libavformat-dev":"ffmpeg","liblilv-dev":"lilv","wx-common":"wxwidgets","libkf5textwidgets-dev":"ktextwidgets","cpio":"cpio","python3-dnspython":"dnspython","libp11-kit-dev":"p11-kit","qml-module-qtquick-controls2":"qtquickcontrols","pciutils":"pciutils","libgtkmm-4.0-dev":"gtkmm","libtss2-mu0":"tpm2-tss","libspatialindex-dev":"libspatialindex","makeself":"makeself","kdoctools5":"kdoctools","patch":"patch","uuid-runtime":"util-linux","puredata-core":"puredata","libspdlog-dev":"spdlog","libmilter-dev":"libmilter","libavcodec-dev":"ffmpeg","libkf5configwidgets-dev":"kconfigwidgets","libftdi1-dev":"libftdi","libsoapysdr-dev":"soapysdr","beancount":"beancount","gir1.2-totemplparser-1.0":"totem-pl-parser","libsemanage-dev":"libsemanage","protobuf-compiler-grpc":"grpc","libucto-dev":"ucto","python3-appdirs":"appdirs","libav-tools":"ffmpeg","libmlt++-dev":"mlt","python3-freezegun":"freezegun","libopusfile-dev":"opusfile","python3-pyside2.qtwebenginewidgets":"pyside2","protobuf-compiler":"protobuf","libheif-dev":"libheif","libglib2.0-bin":"glib","libtheora-dev":"libtheora","libgdal-dev":"gdal","libsdl-dev":"SDL","libkpathsea-dev":"texlive-bin","screen":"screen","uranium-tools":"uranium","libcln-dev":"cln","python3-enlighten":"enlighten","libxosd-dev":"xosd","libxml2-dev":"libxml2","libgdbm-compat-dev":"gdbm","python3-ansi":"ansi","libint2-dev":"libint","libkchart-dev":"kdiagram","libavro-dev":"avro-c","ed":"ed","libxml2-doc":"libxml2","python3-pafy":"pafy","libmediastreamer-dev":"mediastreamer2","python3-setuptools-whl":"setuptools","gnuplot-nox":"gnuplot","gettext":"gettext","mobile-broadband-provider-info":"mobile-broadband-provider-info","libroutino-dev":"routino","librdmacm-dev":"rdma-core","xaw3dg-dev":"Xaw3d","libassuan-dev":"libassuan","python3-sip":"sip","libsqlcipher-dev":"sqlcipher","libccrtp-dev":"ccrtp","gfortran":"gfortran","gir1.2-spiceclientgtk-3.0":"spice-gtk","python3-usb":"pyusb","libmarkdown2-dev":"discount","libselinux-dev":"libselinux","libpinyin15-dev":"libpinyin","libmujs-dev":"mujs","python3-jsonpickle":"jsonpickle","libgtop2-dev":"libgtop","libkomparediff2-dev":"libkomparediff2","backintime-common":"backintime-common","libpcre3-dev":"pcre","jdupes":"jdupes","postgresql-15":"postgresql","gob2":"gob2","lib64ncurses-dev":"ncurses","python3-pykeepass":"pykeepass","libgsound-dev":"gsound","shapelib":"shapelib","libcurl4-nss-dev":"curl","libpq-dev":"postgresql","python3-uinput":"python-uinput","python3-sasmodels":"sasmodels","qml-module-io-thp-pyotherside":"pyotherside","libhiredis-dev":"hiredis","libpeas-dev":"libpeas","libplib-dev":"plib","libxapian-dev":"xapian","libgtk2.0-doc":"gtk+","qemu-system-gui":"qemu","libsigrok-dev":"libsigrok","liboping-dev":"liboping","libext2fs-dev":"e2fsprogs","libksba-dev":"libksba","libzbar-dev":"zbar","python3-docopt":"docopt","liblhasa-dev":"lhasa","libclthreads-dev":"libclthreads","libfmt-dev":"fmt"}