{
  "pkgs_name": "horizon-eda",
  "nix_pkg": null,
  "control_file_hash": "3a074896bcbea30d7f63a18efd154d92d67c2c55fe75cea8e71cb21f9fe7c9c6",
  "deb_inputs": [
    "cppzmq-dev",
    "debhelper",
    "dh-python",
    "doxygen",
    "libarchive-dev",
    "libboost-dev",
    "libcairomm-1.0-dev",
    "libcurl4-gnutls-dev",
    "libdxflib-dev",
    "libepoxy-dev",
    "libgit2-dev",
    "libglib2.0-dev",
    "libglm-dev",
    "libgtkmm-3.0-dev",
    "liboce-ocaf-dev",
    "libosmesa6-dev",
    "libpodofo-dev",
    "libpython3-dev",
    "librsvg2-dev",
    "libspnav-dev",
    "libsqlite3-dev",
    "libzip-dev",
    "libzmq5",
    "python3-cairo-dev",
    "util-linux",
    "uuid-dev"
  ],
  "nix_inputs": [
    "boost",
    "cppzmq",
    "curl",
    "glm",
    "gtkmm",
    "libarchive",
    "libepoxy",
    "libgit2",
    "librsvg",
    "libspnav",
    "opencascade-oce",
    "pkg-config-wrapper",
    "podofo",
    "python3",
    "sqlite",
    "util-linux-minimal",
    "zeromq"
  ],
  "map": {
    "libgtkmm-3.0-dev": "gtkmm",
    "libarchive-dev": "libarchive",
    "libboost-dev": "boost",
    "libcurl4-gnutls-dev": "curl",
    "librsvg2-dev": "librsvg",
    "libspnav-dev": "libspnav",
    "libpodofo-dev": "podofo",
    "libglm-dev": "glm",
    "cppzmq-dev": "cppzmq",
    "libepoxy-dev": "libepoxy",
    "libgit2-dev": "libgit2",
    "libsqlite3-dev": "sqlite",
    "libzmq5": "zeromq"
  }
}
